Workbook

Sheet Sales summary
B2: Monthly Sales Summary — Tankhoone Fashion Retail 2023
B3: Row Labels | C3: Sum of Revenue | D3: Count of Order_ID | E3: Sum of Qty
B4: Jan | C4: 40415250 | D4: 65 | E4: 138
B5: Feb | C5: 31895200 | D5: 68 | E5: 124
B6: Mar | C6: 83066250 | D6: 164 | E6: 302
B7: Apr | C7: 41159750 | D7: 90 | E7: 149
B8: May | C8: 32219750 | D8: 75 | E8: 125
B9: Jun | C9: 45394750 | D9: 89 | E9: 171
B10: Jul | C10: 50704600 | D10: 111 | E10: 189
B11: Aug | C11: 25137150 | D11: 55 | E11: 110
B12: Sep | C12: 56522300 | D12: 109 | E12: 218
B13: Oct | C13: 52349700 | D13: 99 | E13: 188
B14: Nov | C14: 68497050 | D14: 119 | E14: 239
B15: Dec | C15: 66352550 | D15: 145 | E15: 248
B16: Grand Total | C16: 593714300 | D16: 1189 | E16: 2201

Sheet Sales by Categories
B5: Sales by Categories
T8: Co-ord Sets | U8: 193451000
T9: Sweatshirts | U9: 110068750
T10: Dresses | U10: 76313750
B11: Row Labels | C11: Sum of Revenue | D11: Sum of Qty | T11: Knitwear | U11: 53918500
B12: Co-ord Sets | C12: 193451000 | D12: 466 | T12: Outerwear | U12: 49078750
B13: Sweatshirts | C13: 110068750 | D13: 518 | T13: Shirts | U13: 28173300
B14: Dresses | C14: 76313750 | D14: 251 | T14: Knit Dresses | U14: 25104000
B15: Knitwear | C15: 53918500 | D15: 206 | T15: Basics | U15: 19661250
B16: Outerwear | C16: 49078750 | D16: 129 | T16: Skirts | U16: 18708500
B17: Shirts | C17: 28173300 | D17: 148 | T17: Pyjamas | U17: 11001000
B18: Knit Dresses | C18: 25104000 | D18: 80 | T18: Bottoms | U18: 8235500
B19: Basics | C19: 19661250 | D19: 193
B20: Skirts | C20: 18708500 | D20: 113
B21: Pyjamas | C21: 11001000 | D21: 50
B22: Bottoms | C22: 8235500 | D22: 47
B23: Grand Total | C23: 593714300 | D23: 2201

Sheet Sales by Channel
C1: Sales by Channel
B5: Row Labels | C5: Sum of Revenue
B6: Instagram DM | C6: 233673800
B7: in-store | C7: 171736900
B8: Website | C8: 94536600
B9: Telegram | C9: 68506800
B10: Grand Total | C10: 568454100

Sheet Top 10 SKUs by Revenue
D2: Top 10 SKUs by Revenue
C8: Row Labels | D8: Sum of Revenue | E8: Sum of Qty
C9: Beige Co-ord Set | D9: 69678000 | E9: 172
C10: Sage Green Co-ord | D10: 51621500 | E10: 124 | O10: Beige Co-ord Set | P10: 69678000
C11: Orange Linen Set | D11: 50094000 | E11: 117 | O11: Sage Green Co-ord | P11: 51621500
C12: Khaki Cargo Jacket | D12: 49078750 | E12: 129 | O12: Orange Linen Set | P12: 50094000
C13: Pink Sweatshirt | D13: 40513000 | E13: 190 | O13: Khaki Cargo Jacket | P13: 49078750
C14: Olive Sweatshirt | D14: 27563000 | E14: 132 | O14: Pink Sweatshirt | P14: 40513000
C15: Floral Print Dress | D15: 27494000 | E15: 96 | O15: Olive Sweatshirt | P15: 27563000
C16: Burgundy Knit Dress | D16: 25104000 | E16: 80 | O16: Floral Print Dress | P16: 27494000
C17: Cable Knit Vest White | D17: 25012000 | E17: 98 | O17: Burgundy Knit Dress | P17: 25104000
C18: Rust Co-ord Set | D18: 22057500 | E18: 53 | O18: Cable Knit Vest White | P18: 25012000
C19: Grand Total | D19: 388215750 | E19: 1191 | O19: Rust Co-ord Set | P19: 22057500

Sheet Demand Analysis
B2: Sum of Qty | C2: Column Labels
B3: Row Labels | C3: Jan | D3: Feb | E3: Mar | F3: Apr | G3: May | H3: Jun | I3: Jul | J3: Aug | K3: Sep | L3: Oct | M3: Nov | N3: Dec | O3: Grand Total | R3: Row Labels | S3: Jan | T3: Feb | U3: Mar | V3: Apr | W3: May | X3: Jun | Y3: Jul | Z3: Aug | AA3: Sep | AB3: Oct | AC3: Nov | AD3: Dec | AE3: Average Monthly Qty | AF3: Std Dev | AG3: CV | AH3: CV Flag | AI3: Category | AJ3: Slope | AK3: Trend Flag | AM3: Category | AN3: Avg CV | AO3: Count High
B4: PRD-001 | C4: 1 | D4: 3 | E4: 9 | F4: 5 | G4: 1 | H4: 7 | I4: 3 | K4: 5 | L4: 4 | M4: 1 | N4: 2 | O4: 41 | R4: PRD-001 | S4: 1 | T4: 3 | U4: 9 | V4: 5 | W4: 1 | X4: 7 | Y4: 3 | AA4: 5 | AB4: 4 | AC4: 1 | AD4: 2 | AE4: =AVERAGE(S4:AD4) -> 3.7272727 | AF4: =_xlfn.STDEV.P(S4:AD4) -> 2.489648 | AG4: =AF4/AE4 -> 0.66795434 | AH4: =IF(AG4>0.6, "High",IF(AG4>0.3, "Moderate","Stable")) -> High | AI4: =_xlfn.XLOOKUP(R4,Table1[SKU_Code],Table1[Category],"Missing") -> Co-ord Sets | AJ4: =SLOPE(Table17[[#This Row],[Jan]:[Dec]], {1,2,3,4,5,6,7,8,9,10,11,12}) -> -0.13454075 | AK4: =IF(Table17[[#This Row],[Slope]]>5,"Growing", IF(Table17[[#This Row],[Slope]]<-5,"Declining","Flat")) -> Flat | AM4: {=_xlfn.UNIQUE(Table17[Category])} -> Co-ord Sets | AN4: =AVERAGEIF(Table17[Category],AM4,Table17[CV]) -> 0.65747489 | AO4: =COUNTIFS(Table17[Category],AM4,Table17[CV Flag],"High") -> 6
B5: PRD-002 | C5: 2 | D5: 6 | E5: 11 | F5: 1 | G5: 10 | H5: -1 | I5: 5 | J5: 2 | K5: 5 | L5: 11 | M5: 12 | N5: 5 | O5: 69 | R5: PRD-002 | S5: 2 | T5: 6 | U5: 11 | V5: 1 | W5: 10 | X5: -1 | Y5: 5 | Z5: 2 | AA5: 5 | AB5: 11 | AC5: 12 | AD5: 5 | AE5: =AVERAGE(S5:AD5) -> 5.75 | AF5: =_xlfn.STDEV.P(S5:AD5) -> 4.1857895 | AG5: =AF5/AE5 -> 0.72796338 | AH5: =IF(AG5>0.6, "High",IF(AG5>0.3, "Moderate","Stable")) -> High | AI5: =_xlfn.XLOOKUP(R5,Table1[SKU_Code],Table1[Category],"Missing") -> Co-ord Sets | AJ5: =SLOPE(Table17[[#This Row],[Jan]:[Dec]], {1,2,3,4,5,6,7,8,9,10,11,12}) -> 0.31118881 | AK5: =IF(Table17[[#This Row],[Slope]]>5,"Growing", IF(Table17[[#This Row],[Slope]]<-5,"Declining","Flat")) -> Flat | AM5: Sweatshirts | AN5: =AVERAGEIF(Table17[Category],AM5,Table17[CV]) -> 0.75941829 | AO5: =COUNTIFS(Table17[Category],AM5,Table17[CV Flag],"High") -> 6
B6: PRD-003 | D6: 5 | E6: 14 | F6: 1 | G6: 2 | H6: 10 | I6: 3 | J6: 3 | K6: 6 | L6: 3 | M6: 8 | N6: 7 | O6: 62 | R6: PRD-003 | T6: 5 | U6: 14 | V6: 1 | W6: 2 | X6: 10 | Y6: 3 | Z6: 3 | AA6: 6 | AB6: 3 | AC6: 8 | AD6: 7 | AE6: =AVERAGE(S6:AD6) -> 5.6363636 | AF6: =_xlfn.STDEV.P(S6:AD6) -> 3.7239453 | AG6: =AF6/AE6 -> 0.66069997 | AH6: =IF(AG6>0.6, "High",IF(AG6>0.3, "Moderate","Stable")) -> High | AI6: =_xlfn.XLOOKUP(R6,Table1[SKU_Code],Table1[Category],"Missing") -> Co-ord Sets | AJ6: =SLOPE(Table17[[#This Row],[Jan]:[Dec]], {1,2,3,4,5,6,7,8,9,10,11,12}) -> -0.063636364 | AK6: =IF(Table17[[#This Row],[Slope]]>5,"Growing", IF(Table17[[#This Row],[Slope]]<-5,"Declining","Flat")) -> Flat | AM6: Knit Dresses | AN6: =AVERAGEIF(Table17[Category],AM6,Table17[CV]) -> 0.86292695 | AO6: =COUNTIFS(Table17[Category],AM6,Table17[CV Flag],"High") -> 2
B7: PRD-004 | D7: 3 | E7: 1 | F7: 5 | G7: 9 | H7: 3 | I7: 3 | J7: 9 | K7: 3 | L7: 11 | M7: 9 | N7: 7 | O7: 63 | R7: PRD-004 | T7: 3 | U7: 1 | V7: 5 | W7: 9 | X7: 3 | Y7: 3 | Z7: 9 | AA7: 3 | AB7: 11 | AC7: 9 | AD7: 7 | AE7: =AVERAGE(S7:AD7) -> 5.7272727 | AF7: =_xlfn.STDEV.P(S7:AD7) -> 3.2218264 | AG7: =AF7/AE7 -> 0.56254112 | AH7: =IF(AG7>0.6, "High",IF(AG7>0.3, "Moderate","Stable")) -> Moderate | AI7: =_xlfn.XLOOKUP(R7,Table1[SKU_Code],Table1[Category],"Missing") -> Sweatshirts | AJ7: =SLOPE(Table17[[#This Row],[Jan]:[Dec]], {1,2,3,4,5,6,7,8,9,10,11,12}) -> 0.58181818 | AK7: =IF(Table17[[#This Row],[Slope]]>5,"Growing", IF(Table17[[#This Row],[Slope]]<-5,"Declining","Flat")) -> Flat | AM7: Knitwear | AN7: =AVERAGEIF(Table17[Category],AM7,Table17[CV]) -> 0.69132162 | AO7: =COUNTIFS(Table17[Category],AM7,Table17[CV Flag],"High") -> 4
B8: PRD-005 | C8: 1 | D8: 8 | E8: 8 | F8: 3 | H8: 2 | I8: 6 | J8: 12 | K8: 15 | M8: 5 | N8: 8 | O8: 68 | R8: PRD-005 | S8: 1 | T8: 8 | U8: 8 | V8: 3 | X8: 2 | Y8: 6 | Z8: 12 | AA8: 15 | AC8: 5 | AD8: 8 | AE8: =AVERAGE(S8:AD8) -> 6.8 | AF8: =_xlfn.STDEV.P(S8:AD8) -> 4.1665333 | AG8: =AF8/AE8 -> 0.61272549 | AH8: =IF(AG8>0.6, "High",IF(AG8>0.3, "Moderate","Stable")) -> High | AI8: =_xlfn.XLOOKUP(R8,Table1[SKU_Code],Table1[Category],"Missing") -> Sweatshirts | AJ8: =SLOPE(Table17[[#This Row],[Jan]:[Dec]], {1,2,3,4,5,6,7,8,9,10,11,12}) -> 0.47306792 | AK8: =IF(Table17[[#This Row],[Slope]]>5,"Growing", IF(Table17[[#This Row],[Slope]]<-5,"Declining","Flat")) -> Flat | AM8: Shirts | AN8: =AVERAGEIF(Table17[Category],AM8,Table17[CV]) -> 0.68341424 | AO8: =COUNTIFS(Table17[Category],AM8,Table17[CV Flag],"High") -> 3
B9: PRD-006 | C9: 8 | D9: 4 | E9: 14 | F9: 3 | G9: 3 | H9: 5 | I9: -2 | J9: 2 | K9: 9 | L9: 3 | M9: 4 | N9: 6 | O9: 59 | R9: PRD-006 | S9: 8 | T9: 4 | U9: 14 | V9: 3 | W9: 3 | X9: 5 | Y9: -2 | Z9: 2 | AA9: 9 | AB9: 3 | AC9: 4 | AD9: 6 | AE9: =AVERAGE(S9:AD9) -> 4.9166667 | AF9: =_xlfn.STDEV.P(S9:AD9) -> 3.8613109 | AG9: =AF9/AE9 -> 0.78535138 | AH9: =IF(AG9>0.6, "High",IF(AG9>0.3, "Moderate","Stable")) -> High | AI9: =_xlfn.XLOOKUP(R9,Table1[SKU_Code],Table1[Category],"Missing") -> Sweatshirts | AJ9: =SLOPE(Table17[[#This Row],[Jan]:[Dec]], {1,2,3,4,5,6,7,8,9,10,11,12}) -> -0.27622378 | AK9: =IF(Table17[[#This Row],[Slope]]>5,"Growing", IF(Table17[[#This Row],[Slope]]<-5,"Declining","Flat")) -> Flat | AM9: Skirts | AN9: =AVERAGEIF(Table17[Category],AM9,Table17[CV]) -> 0.57864058 | AO9: =COUNTIFS(Table17[Category],AM9,Table17[CV Flag],"High") -> 1
B10: PRD-007 | C10: 4 | D10: 4 | E10: 3 | G10: 5 | H10: 7 | I10: 12 | J10: 2 | K10: 6 | L10: 10 | M10: 2 | N10: 3 | O10: 58 | R10: PRD-007 | S10: 4 | T10: 4 | U10: 3 | W10: 5 | X10: 7 | Y10: 12 | Z10: 2 | AA10: 6 | AB10: 10 | AC10: 2 | AD10: 3 | AE10: =AVERAGE(S10:AD10) -> 5.2727273 | AF10: =_xlfn.STDEV.P(S10:AD10) -> 3.1069105 | AG10: =AF10/AE10 -> 0.58924164 | AH10: =IF(AG10>0.6, "High",IF(AG10>0.3, "Moderate","Stable")) -> Moderate | AI10: =_xlfn.XLOOKUP(R10,Table1[SKU_Code],Table1[Category],"Missing") -> Sweatshirts | AJ10: =SLOPE(Table17[[#This Row],[Jan]:[Dec]], {1,2,3,4,5,6,7,8,9,10,11,12}) -> 0.072096128 | AK10: =IF(Table17[[#This Row],[Slope]]>5,"Growing", IF(Table17[[#This Row],[Slope]]<-5,"Declining","Flat")) -> Flat | AM10: Dresses | AN10: =AVERAGEIF(Table17[Category],AM10,Table17[CV]) -> 0.71883969 | AO10: =COUNTIFS(Table17[Category],AM10,Table17[CV Flag],"High") -> 5
B11: PRD-008 | C11: 4 | D11: 17 | E11: 8 | F11: 6 | H11: 2 | I11: 12 | J11: 3 | K11: 2 | L11: 4 | M11: 13 | N11: 3 | O11: 74 | R11: PRD-008 | S11: 4 | T11: 17 | U11: 8 | V11: 6 | X11: 2 | Y11: 12 | Z11: 3 | AA11: 2 | AB11: 4 | AC11: 13 | AD11: 3 | AE11: =AVERAGE(S11:AD11) -> 6.7272727 | AF11: =_xlfn.STDEV.P(S11:AD11) -> 4.8820806 | AG11: =AF11/AE11 -> 0.72571468 | AH11: =IF(AG11>0.6, "High",IF(AG11>0.3, "Moderate","Stable")) -> High | AI11: =_xlfn.XLOOKUP(R11,Table1[SKU_Code],Table1[Category],"Missing") -> Sweatshirts | AJ11: =SLOPE(Table17[[#This Row],[Jan]:[Dec]], {1,2,3,4,5,6,7,8,9,10,11,12}) -> -0.34217335 | AK11: =IF(Table17[[#This Row],[Slope]]>5,"Growing", IF(Table17[[#This Row],[Slope]]<-5,"Declining","Flat")) -> Flat | AM11: Outerwear | AN11: =AVERAGEIF(Table17[Category],AM11,Table17[CV]) -> 0.7685986 | AO11: =COUNTIFS(Table17[Category],AM11,Table17[CV Flag],"High") -> 1
B12: PRD-009 | C12: 5 | D12: 3 | E12: 3 | F12: 2 | G12: 12 | H12: 10 | I12: 6 | K12: 9 | L12: 3 | M12: 11 | N12: 7 | O12: 71 | R12: PRD-009 | S12: 5 | T12: 3 | U12: 3 | V12: 2 | W12: 12 | X12: 10 | Y12: 6 | AA12: 9 | AB12: 3 | AC12: 11 | AD12: 7 | AE12: =AVERAGE(S12:AD12) -> 6.4545455 | AF12: =_xlfn.STDEV.P(S12:AD12) -> 3.4208887 | AG12: =AF12/AE12 -> 0.52999684 | AH12: =IF(AG12>0.6, "High",IF(AG12>0.3, "Moderate","Stable")) -> Moderate | AI12: =_xlfn.XLOOKUP(R12,Table1[SKU_Code],Table1[Category],"Missing") -> Sweatshirts | AJ12: =SLOPE(Table17[[#This Row],[Jan]:[Dec]], {1,2,3,4,5,6,7,8,9,10,11,12}) -> 0.385511 | AK12: =IF(Table17[[#This Row],[Slope]]>5,"Growing", IF(Table17[[#This Row],[Slope]]<-5,"Declining","Flat")) -> Flat | AM12: Pyjamas | AN12: =AVERAGEIF(Table17[Category],AM12,Table17[CV]) -> 0.91214034 | AO12: =COUNTIFS(Table17[Category],AM12,Table17[CV Flag],"High") -> 1
B13: PRD-010 | C13: 4 | D13: 2 | E13: 1 | F13: 0 | G13: 5 | H13: 8 | I13: 2 | J13: 2 | K13: 7 | L13: 4 | M13: 5 | O13: 40 | R13: PRD-010 | S13: 4 | T13: 2 | U13: 1 | V13: 0 | W13: 5 | X13: 8 | Y13: 2 | Z13: 2 | AA13: 7 | AB13: 4 | AC13: 5 | AE13: =AVERAGE(S13:AD13) -> 3.6363636 | AF13: =_xlfn.STDEV.P(S13:AD13) -> 2.3845231 | AG13: =AF13/AE13 -> 0.65574385 | AH13: =IF(AG13>0.6, "High",IF(AG13>0.3, "Moderate","Stable")) -> High | AI13: =_xlfn.XLOOKUP(R13,Table1[SKU_Code],Table1[Category],"Missing") -> Sweatshirts | AJ13: =SLOPE(Table17[[#This Row],[Jan]:[Dec]], {1,2,3,4,5,6,7,8,9,10,11,12}) -> 0.29090909 | AK13: =IF(Table17[[#This Row],[Slope]]>5,"Growing", IF(Table17[[#This Row],[Slope]]<-5,"Declining","Flat")) -> Flat | AM13: Basics | AN13: =AVERAGEIF(Table17[Category],AM13,Table17[CV]) -> 0.65234596 | AO13: =COUNTIFS(Table17[Category],AM13,Table17[CV Flag],"High") -> 2
B14: PRD-011 | C14: 7 | D14: 3 | E14: 2 | F14: 1 | I14: -3 | J14: 3 | K14: 8 | L14: 8 | M14: 7 | N14: 2 | O14: 38 | R14: PRD-011 | S14: 7 | T14: 3 | U14: 2 | V14: 1 | Y14: -3 | Z14: 3 | AA14: 8 | AB14: 8 | AC14: 7 | AD14: 2 | AE14: =AVERAGE(S14:AD14) -> 3.8 | AF14: =_xlfn.STDEV.P(S14:AD14) -> 3.4292856 | AG14: =AF14/AE14 -> 0.90244359 | AH14: =IF(AG14>0.6, "High",IF(AG14>0.3, "Moderate","Stable")) -> High | AI14: =_xlfn.XLOOKUP(R14,Table1[SKU_Code],Table1[Category],"Missing") -> Knit Dresses | AJ14: =SLOPE(Table17[[#This Row],[Jan]:[Dec]], {1,2,3,4,5,6,7,8,9,10,11,12}) -> 0.17416131 | AK14: =IF(Table17[[#This Row],[Slope]]>5,"Growing", IF(Table17[[#This Row],[Slope]]<-5,"Declining","Flat")) -> Flat | AM14: Bottoms | AN14: =AVERAGEIF(Table17[Category],AM14,Table17[CV]) -> 0.60778114 | AO14: =COUNTIFS(Table17[Category],AM14,Table17[CV Flag],"High") -> 1
B15: PRD-012 | C15: 4 | E15: 2 | F15: 13 | H15: 3 | I15: 7 | J15: 2 | K15: 6 | L15: 2 | M15: 2 | N15: 1 | O15: 42 | R15: PRD-012 | S15: 4 | U15: 2 | V15: 13 | X15: 3 | Y15: 7 | Z15: 2 | AA15: 6 | AB15: 2 | AC15: 2 | AD15: 1 | AE15: =AVERAGE(S15:AD15) -> 4.2 | AF15: =_xlfn.STDEV.P(S15:AD15) -> 3.4583233 | AG15: =AF15/AE15 -> 0.82341031 | AH15: =IF(AG15>0.6, "High",IF(AG15>0.3, "Moderate","Stable")) -> High | AI15: =_xlfn.XLOOKUP(R15,Table1[SKU_Code],Table1[Category],"Missing") -> Knit Dresses | AJ15: =SLOPE(Table17[[#This Row],[Jan]:[Dec]], {1,2,3,4,5,6,7,8,9,10,11,12}) -> -0.38665526 | AK15: =IF(Table17[[#This Row],[Slope]]>5,"Growing", IF(Table17[[#This Row],[Slope]]<-5,"Declining","Flat")) -> Flat
B16: PRD-013 | C16: 4 | D16: 6 | E16: 5 | F16: 6 | G16: 0 | H16: 1 | I16: 8 | J16: 5 | K16: 2 | L16: 10 | M16: 10 | N16: 4 | O16: 61 | R16: PRD-013 | S16: 4 | T16: 6 | U16: 5 | V16: 6 | W16: 0 | X16: 1 | Y16: 8 | Z16: 5 | AA16: 2 | AB16: 10 | AC16: 10 | AD16: 4 | AE16: =AVERAGE(S16:AD16) -> 5.0833333 | AF16: =_xlfn.STDEV.P(S16:AD16) -> 3.0675271 | AG16: =AF16/AE16 -> 0.60344794 | AH16: =IF(AG16>0.6, "High",IF(AG16>0.3, "Moderate","Stable")) -> High | AI16: =_xlfn.XLOOKUP(R16,Table1[SKU_Code],Table1[Category],"Missing") -> Knitwear | AJ16: =SLOPE(Table17[[#This Row],[Jan]:[Dec]], {1,2,3,4,5,6,7,8,9,10,11,12}) -> 0.25524476 | AK16: =IF(Table17[[#This Row],[Slope]]>5,"Growing", IF(Table17[[#This Row],[Slope]]<-5,"Declining","Flat")) -> Flat
B17: PRD-014 | C17: 3 | D17: 3 | E17: 2 | F17: 9 | G17: 5 | H17: 1 | I17: 15 | J17: 3 | K17: 8 | N17: 6 | O17: 55 | R17: PRD-014 | S17: 3 | T17: 3 | U17: 2 | V17: 9 | W17: 5 | X17: 1 | Y17: 15 | Z17: 3 | AA17: 8 | AD17: 6 | AE17: =AVERAGE(S17:AD17) -> 5.5 | AF17: =_xlfn.STDEV.P(S17:AD17) -> 4.0062451 | AG17: =AF17/AE17 -> 0.7284082 | AH17: =IF(AG17>0.6, "High",IF(AG17>0.3, "Moderate","Stable")) -> High | AI17: =_xlfn.XLOOKUP(R17,Table1[SKU_Code],Table1[Category],"Missing") -> Knitwear | AJ17: =SLOPE(Table17[[#This Row],[Jan]:[Dec]], {1,2,3,4,5,6,7,8,9,10,11,12}) -> 0.39865514 | AK17: =IF(Table17[[#This Row],[Slope]]>5,"Growing", IF(Table17[[#This Row],[Slope]]<-5,"Declining","Flat")) -> Flat
B18: PRD-015 | C18: 0 | D18: 5 | E18: 8 | F18: 2 | G18: 6 | I18: 1 | J18: 3 | L18: 5 | M18: 10 | N18: 3 | O18: 43 | R18: PRD-015 | S18: 0 | T18: 5 | U18: 8 | V18: 2 | W18: 6 | Y18: 1 | Z18: 3 | AB18: 5 | AC18: 10 | AD18: 3 | AE18: =AVERAGE(S18:AD18) -> 4.3 | AF18: =_xlfn.STDEV.P(S18:AD18) -> 2.9681644 | AG18: =AF18/AE18 -> 0.69027079 | AH18: =IF(AG18>0.6, "High",IF(AG18>0.3, "Moderate","Stable")) -> High | AI18: =_xlfn.XLOOKUP(R18,Table1[SKU_Code],Table1[Category],"Missing") -> Knitwear | AJ18: =SLOPE(Table17[[#This Row],[Jan]:[Dec]], {1,2,3,4,5,6,7,8,9,10,11,12}) -> 0.20646583 | AK18: =IF(Table17[[#This Row],[Slope]]>5,"Growing", IF(Table17[[#This Row],[Slope]]<-5,"Declining","Flat")) -> Flat
B19: PRD-016 | C19: 3 | D19: 1 | E19: 9 | F19: 2 | G19: 3 | H19: 1 | I19: 2 | J19: 1 | K19: 4 | L19: 2 | M19: 2 | N19: 9 | O19: 39 | R19: PRD-016 | S19: 3 | T19: 1 | U19: 9 | V19: 2 | W19: 3 | X19: 1 | Y19: 2 | Z19: 1 | AA19: 4 | AB19: 2 | AC19: 2 | AD19: 9 | AE19: =AVERAGE(S19:AD19) -> 3.25 | AF19: =_xlfn.STDEV.P(S19:AD19) -> 2.7118567 | AG19: =AF19/AE19 -> 0.83441744 | AH19: =IF(AG19>0.6, "High",IF(AG19>0.3, "Moderate","Stable")) -> High | AI19: =_xlfn.XLOOKUP(R19,Table1[SKU_Code],Table1[Category],"Missing") -> Sweatshirts | AJ19: =SLOPE(Table17[[#This Row],[Jan]:[Dec]], {1,2,3,4,5,6,7,8,9,10,11,12}) -> 0.10839161 | AK19: =IF(Table17[[#This Row],[Slope]]>5,"Growing", IF(Table17[[#This Row],[Slope]]<-5,"Declining","Flat")) -> Flat
B20: PRD-017 | C20: 2 | D20: 1 | E20: 22 | G20: 1 | H20: 1 | I20: 8 | J20: 1 | K20: 2 | L20: 6 | M20: -4 | N20: 6 | O20: 46 | R20: PRD-017 | S20: 2 | T20: 1 | U20: 22 | W20: 1 | X20: 1 | Y20: 8 | Z20: 1 | AA20: 2 | AB20: 6 | AC20: -4 | AD20: 6 | AE20: =AVERAGE(S20:AD20) -> 4.1818182 | AF20: =_xlfn.STDEV.P(S20:AD20) -> 6.4359527 | AG20: =AF20/AE20 -> 1.5390322 | AH20: =IF(AG20>0.6, "High",IF(AG20>0.3, "Moderate","Stable")) -> High | AI20: =_xlfn.XLOOKUP(R20,Table1[SKU_Code],Table1[Category],"Missing") -> Sweatshirts | AJ20: =SLOPE(Table17[[#This Row],[Jan]:[Dec]], {1,2,3,4,5,6,7,8,9,10,11,12}) -> -0.42923899 | AK20: =IF(Table17[[#This Row],[Slope]]>5,"Growing", IF(Table17[[#This Row],[Slope]]<-5,"Declining","Flat")) -> Flat
B21: PRD-018 | C21: 4 | E21: 11 | H21: 6 | I21: 4 | K21: 2 | L21: 3 | M21: 14 | N21: 2 | O21: 46 | R21: PRD-018 | S21: 4 | U21: 11 | X21: 6 | Y21: 4 | AA21: 2 | AB21: 3 | AC21: 14 | AD21: 2 | AE21: =AVERAGE(S21:AD21) -> 5.75 | AF21: =_xlfn.STDEV.P(S21:AD21) -> 4.145781 | AG21: =AF21/AE21 -> 0.72100539 | AH21: =IF(AG21>0.6, "High",IF(AG21>0.3, "Moderate","Stable")) -> High | AI21: =_xlfn.XLOOKUP(R21,Table1[SKU_Code],Table1[Category],"Missing") -> Shirts | AJ21: =SLOPE(Table17[[#This Row],[Jan]:[Dec]], {1,2,3,4,5,6,7,8,9,10,11,12}) -> -0.11570248 | AK21: =IF(Table17[[#This Row],[Slope]]>5,"Growing", IF(Table17[[#This Row],[Slope]]<-5,"Declining","Flat")) -> Flat
B22: PRD-019 | C22: 1 | E22: 9 | F22: 5 | G22: 4 | H22: 6 | I22: 4 | J22: 1 | K22: 13 | L22: 4 | M22: 2 | N22: 5 | O22: 54 | R22: PRD-019 | S22: 1 | U22: 9 | V22: 5 | W22: 4 | X22: 6 | Y22: 4 | Z22: 1 | AA22: 13 | AB22: 4 | AC22: 2 | AD22: 5 | AE22: =AVERAGE(S22:AD22) -> 4.9090909 | AF22: =_xlfn.STDEV.P(S22:AD22) -> 3.3697733 | AG22: =AF22/AE22 -> 0.6864353 | AH22: =IF(AG22>0.6, "High",IF(AG22>0.3, "Moderate","Stable")) -> High | AI22: =_xlfn.XLOOKUP(R22,Table1[SKU_Code],Table1[Category],"Missing") -> Shirts | AJ22: =SLOPE(Table17[[#This Row],[Jan]:[Dec]], {1,2,3,4,5,6,7,8,9,10,11,12}) -> 0.04887218 | AK22: =IF(Table17[[#This Row],[Slope]]>5,"Growing", IF(Table17[[#This Row],[Slope]]<-5,"Declining","Flat")) -> Flat
B23: PRD-020 | C23: 2 | D23: 8 | E23: 0 | F23: 7 | G23: 4 | H23: 1 | I23: 6 | J23: 2 | K23: 9 | L23: 4 | N23: 5 | O23: 48 | R23: PRD-020 | S23: 2 | T23: 8 | U23: 0 | V23: 7 | W23: 4 | X23: 1 | Y23: 6 | Z23: 2 | AA23: 9 | AB23: 4 | AD23: 5 | AE23: =AVERAGE(S23:AD23) -> 4.3636364 | AF23: =_xlfn.STDEV.P(S23:AD23) -> 2.8049543 | AG23: =AF23/AE23 -> 0.64280203 | AH23: =IF(AG23>0.6, "High",IF(AG23>0.3, "Moderate","Stable")) -> High | AI23: =_xlfn.XLOOKUP(R23,Table1[SKU_Code],Table1[Category],"Missing") -> Shirts | AJ23: =SLOPE(Table17[[#This Row],[Jan]:[Dec]], {1,2,3,4,5,6,7,8,9,10,11,12}) -> 0.15413534 | AK23: =IF(Table17[[#This Row],[Slope]]>5,"Growing", IF(Table17[[#This Row],[Slope]]<-5,"Declining","Flat")) -> Flat
B24: PRD-021 | C24: 14 | D24: 4 | E24: 10 | F24: 7 | G24: 7 | H24: 1 | I24: 4 | J24: 2 | K24: 4 | L24: 3 | M24: 8 | N24: 5 | O24: 69 | R24: PRD-021 | S24: 14 | T24: 4 | U24: 10 | V24: 7 | W24: 7 | X24: 1 | Y24: 4 | Z24: 2 | AA24: 4 | AB24: 3 | AC24: 8 | AD24: 5 | AE24: =AVERAGE(S24:AD24) -> 5.75 | AF24: =_xlfn.STDEV.P(S24:AD24) -> 3.5148495 | AG24: =AF24/AE24 -> 0.61127817 | AH24: =IF(AG24>0.6, "High",IF(AG24>0.3, "Moderate","Stable")) -> High | AI24: =_xlfn.XLOOKUP(R24,Table1[SKU_Code],Table1[Category],"Missing") -> Co-ord Sets | AJ24: =SLOPE(Table17[[#This Row],[Jan]:[Dec]], {1,2,3,4,5,6,7,8,9,10,11,12}) -> -0.48601399 | AK24: =IF(Table17[[#This Row],[Slope]]>5,"Growing", IF(Table17[[#This Row],[Slope]]<-5,"Declining","Flat")) -> Flat
B25: PRD-022 | C25: 2 | E25: 4 | F25: 9 | G25: 2 | H25: 2 | I25: 1 | J25: 4 | K25: 5 | L25: 2 | M25: 15 | N25: 9 | O25: 55 | R25: PRD-022 | S25: 2 | U25: 4 | V25: 9 | W25: 2 | X25: 2 | Y25: 1 | Z25: 4 | AA25: 5 | AB25: 2 | AC25: 15 | AD25: 9 | AE25: =AVERAGE(S25:AD25) -> 5 | AF25: =_xlfn.STDEV.P(S25:AD25) -> 4.1120665 | AG25: =AF25/AE25 -> 0.8224133 | AH25: =IF(AG25>0.6, "High",IF(AG25>0.3, "Moderate","Stable")) -> High | AI25: =_xlfn.XLOOKUP(R25,Table1[SKU_Code],Table1[Category],"Missing") -> Co-ord Sets | AJ25: =SLOPE(Table17[[#This Row],[Jan]:[Dec]], {1,2,3,4,5,6,7,8,9,10,11,12}) -> 0.57067669 | AK25: =IF(Table17[[#This Row],[Slope]]>5,"Growing", IF(Table17[[#This Row],[Slope]]<-5,"Declining","Flat")) -> Flat
B26: PRD-023 | C26: 1 | D26: 1 | E26: 8 | G26: 0 | H26: 4 | I26: 6 | J26: 2 | K26: 4 | L26: 6 | M26: 10 | N26: 5 | O26: 47 | R26: PRD-023 | S26: 1 | T26: 1 | U26: 8 | W26: 0 | X26: 4 | Y26: 6 | Z26: 2 | AA26: 4 | AB26: 6 | AC26: 10 | AD26: 5 | AE26: =AVERAGE(S26:AD26) -> 4.2727273 | AF26: =_xlfn.STDEV.P(S26:AD26) -> 2.9875776 | AG26: =AF26/AE26 -> 0.69922029 | AH26: =IF(AG26>0.6, "High",IF(AG26>0.3, "Moderate","Stable")) -> High | AI26: =_xlfn.XLOOKUP(R26,Table1[SKU_Code],Table1[Category],"Missing") -> Co-ord Sets | AJ26: =SLOPE(Table17[[#This Row],[Jan]:[Dec]], {1,2,3,4,5,6,7,8,9,10,11,12}) -> 0.43190921 | AK26: =IF(Table17[[#This Row],[Slope]]>5,"Growing", IF(Table17[[#This Row],[Slope]]<-5,"Declining","Flat")) -> Flat
B27: PRD-024 | C27: 6 | E27: 9 | G27: 2 | H27: 6 | I27: 4 | K27: 4 | L27: 12 | M27: 17 | N27: 10 | O27: 70 | R27: PRD-024 | S27: 6 | U27: 9 | W27: 2 | X27: 6 | Y27: 4 | AA27: 4 | AB27: 12 | AC27: 17 | AD27: 10 | AE27: =AVERAGE(S27:AD27) -> 7.7777778 | AF27: =_xlfn.STDEV.P(S27:AD27) -> 4.4416658 | AG27: =AF27/AE27 -> 0.57107132 | AH27: =IF(AG27>0.6, "High",IF(AG27>0.3, "Moderate","Stable")) -> Moderate | AI27: =_xlfn.XLOOKUP(R27,Table1[SKU_Code],Table1[Category],"Missing") -> Co-ord Sets | AJ27: =SLOPE(Table17[[#This Row],[Jan]:[Dec]], {1,2,3,4,5,6,7,8,9,10,11,12}) -> 0.65130261 | AK27: =IF(Table17[[#This Row],[Slope]]>5,"Growing", IF(Table17[[#This Row],[Slope]]<-5,"Declining","Flat")) -> Flat
B28: PRD-025 | C28: 5 | D28: 6 | E28: 3 | F28: 3 | G28: 7 | H28: 9 | I28: 3 | J28: 4 | K28: 4 | L28: 4 | M28: 11 | N28: 3 | O28: 62 | R28: PRD-025 | S28: 5 | T28: 6 | U28: 3 | V28: 3 | W28: 7 | X28: 9 | Y28: 3 | Z28: 4 | AA28: 4 | AB28: 4 | AC28: 11 | AD28: 3 | AE28: =AVERAGE(S28:AD28) -> 5.1666667 | AF28: =_xlfn.STDEV.P(S28:AD28) -> 2.5110865 | AG28: =AF28/AE28 -> 0.48601675 | AH28: =IF(AG28>0.6, "High",IF(AG28>0.3, "Moderate","Stable")) -> Moderate | AI28: =_xlfn.XLOOKUP(R28,Table1[SKU_Code],Table1[Category],"Missing") -> Skirts | AJ28: =SLOPE(Table17[[#This Row],[Jan]:[Dec]], {1,2,3,4,5,6,7,8,9,10,11,12}) -> 0.06993007 | AK28: =IF(Table17[[#This Row],[Slope]]>5,"Growing", IF(Table17[[#This Row],[Slope]]<-5,"Declining","Flat")) -> Flat
B29: PRD-026 | C29: 3 | E29: 5 | F29: 1 | G29: 2 | H29: 2 | I29: 5 | J29: 6 | K29: 11 | L29: 3 | M29: 3 | N29: 10 | O29: 51 | R29: PRD-026 | S29: 3 | U29: 5 | V29: 1 | W29: 2 | X29: 2 | Y29: 5 | Z29: 6 | AA29: 11 | AB29: 3 | AC29: 3 | AD29: 10 | AE29: =AVERAGE(S29:AD29) -> 4.6363636 | AF29: =_xlfn.STDEV.P(S29:AD29) -> 3.112226 | AG29: =AF29/AE29 -> 0.67126442 | AH29: =IF(AG29>0.6, "High",IF(AG29>0.3, "Moderate","Stable")) -> High | AI29: =_xlfn.XLOOKUP(R29,Table1[SKU_Code],Table1[Category],"Missing") -> Skirts | AJ29: =SLOPE(Table17[[#This Row],[Jan]:[Dec]], {1,2,3,4,5,6,7,8,9,10,11,12}) -> 0.46842105 | AK29: =IF(Table17[[#This Row],[Slope]]>5,"Growing", IF(Table17[[#This Row],[Slope]]<-5,"Declining","Flat")) -> Flat
B30: PRD-027 | C30: 4 | D30: 3 | E30: 13 | F30: 2 | H30: 7 | I30: 3 | K30: 4 | L30: 4 | M30: 2 | N30: 7 | O30: 49 | R30: PRD-027 | S30: 4 | T30: 3 | U30: 13 | V30: 2 | X30: 7 | Y30: 3 | AA30: 4 | AB30: 4 | AC30: 2 | AD30: 7 | AE30: =AVERAGE(S30:AD30) -> 4.9 | AF30: =_xlfn.STDEV.P(S30:AD30) -> 3.176476 | AG30: =AF30/AE30 -> 0.64826042 | AH30: =IF(AG30>0.6, "High",IF(AG30>0.3, "Moderate","Stable")) -> High | AI30: =_xlfn.XLOOKUP(R30,Table1[SKU_Code],Table1[Category],"Missing") -> Dresses | AJ30: =SLOPE(Table17[[#This Row],[Jan]:[Dec]], {1,2,3,4,5,6,7,8,9,10,11,12}) -> -0.11913357 | AK30: =IF(Table17[[#This Row],[Slope]]>5,"Growing", IF(Table17[[#This Row],[Slope]]<-5,"Declining","Flat")) -> Flat
B31: PRD-028 | C31: 3 | D31: 5 | E31: 9 | F31: 3 | G31: 1 | H31: 1 | I31: 3 | J31: 1 | K31: 7 | L31: 4 | M31: 3 | N31: 7 | O31: 47 | R31: PRD-028 | S31: 3 | T31: 5 | U31: 9 | V31: 3 | W31: 1 | X31: 1 | Y31: 3 | Z31: 1 | AA31: 7 | AB31: 4 | AC31: 3 | AD31: 7 | AE31: =AVERAGE(S31:AD31) -> 3.9166667 | AF31: =_xlfn.STDEV.P(S31:AD31) -> 2.4986107 | AG31: =AF31/AE31 -> 0.63794316 | AH31: =IF(AG31>0.6, "High",IF(AG31>0.3, "Moderate","Stable")) -> High | AI31: =_xlfn.XLOOKUP(R31,Table1[SKU_Code],Table1[Category],"Missing") -> Dresses | AJ31: =SLOPE(Table17[[#This Row],[Jan]:[Dec]], {1,2,3,4,5,6,7,8,9,10,11,12}) -> 0.045454545 | AK31: =IF(Table17[[#This Row],[Slope]]>5,"Growing", IF(Table17[[#This Row],[Slope]]<-5,"Declining","Flat")) -> Flat
B32: PRD-029 | C32: 1 | E32: 13 | F32: 4 | G32: 8 | H32: 2 | I32: 2 | J32: 2 | K32: 5 | L32: 5 | M32: 5 | N32: 12 | O32: 59 | R32: PRD-029 | S32: 1 | U32: 13 | V32: 4 | W32: 8 | X32: 2 | Y32: 2 | Z32: 2 | AA32: 5 | AB32: 5 | AC32: 5 | AD32: 12 | AE32: =AVERAGE(S32:AD32) -> 5.3636364 | AF32: =_xlfn.STDEV.P(S32:AD32) -> 3.867645 | AG32: =AF32/AE32 -> 0.72108635 | AH32: =IF(AG32>0.6, "High",IF(AG32>0.3, "Moderate","Stable")) -> High | AI32: =_xlfn.XLOOKUP(R32,Table1[SKU_Code],Table1[Category],"Missing") -> Dresses | AJ32: =SLOPE(Table17[[#This Row],[Jan]:[Dec]], {1,2,3,4,5,6,7,8,9,10,11,12}) -> 0.20150376 | AK32: =IF(Table17[[#This Row],[Slope]]>5,"Growing", IF(Table17[[#This Row],[Slope]]<-5,"Declining","Flat")) -> Flat
B33: PRD-030 | C33: 1 | E33: 14 | F33: 4 | G33: 5 | H33: 6 | I33: 13 | J33: 3 | K33: 1 | L33: 2 | N33: 6 | O33: 55 | R33: PRD-030 | S33: 1 | U33: 14 | V33: 4 | W33: 5 | X33: 6 | Y33: 13 | Z33: 3 | AA33: 1 | AB33: 2 | AD33: 6 | AE33: =AVERAGE(S33:AD33) -> 5.5 | AF33: =_xlfn.STDEV.P(S33:AD33) -> 4.3646306 | AG33: =AF33/AE33 -> 0.79356919 | AH33: =IF(AG33>0.6, "High",IF(AG33>0.3, "Moderate","Stable")) -> High | AI33: =_xlfn.XLOOKUP(R33,Table1[SKU_Code],Table1[Category],"Missing") -> Dresses | AJ33: =SLOPE(Table17[[#This Row],[Jan]:[Dec]], {1,2,3,4,5,6,7,8,9,10,11,12}) -> -0.2097561 | AK33: =IF(Table17[[#This Row],[Slope]]>5,"Growing", IF(Table17[[#This Row],[Slope]]<-5,"Declining","Flat")) -> Flat
B34: PRD-031 | C34: 12 | D34: 4 | E34: 5 | F34: 7 | H34: 3 | I34: 2 | J34: 4 | K34: 10 | L34: 10 | M34: 9 | N34: 8 | O34: 74 | R34: PRD-031 | S34: 12 | T34: 4 | U34: 5 | V34: 7 | X34: 3 | Y34: 2 | Z34: 4 | AA34: 10 | AB34: 10 | AC34: 9 | AD34: 8 | AE34: =AVERAGE(S34:AD34) -> 6.7272727 | AF34: =_xlfn.STDEV.P(S34:AD34) -> 3.16489 | AH34: Excluded — insufficient data | AI34: =_xlfn.XLOOKUP(R34,Table1[SKU_Code],Table1[Category],"Missing") -> Outerwear | AJ34: =SLOPE(Table17[[#This Row],[Jan]:[Dec]], {1,2,3,4,5,6,7,8,9,10,11,12}) -> 0.14877102 | AK34: =IF(Table17[[#This Row],[Slope]]>5,"Growing", IF(Table17[[#This Row],[Slope]]<-5,"Declining","Flat")) -> Flat
B35: PRD-032 | C35: 4 | D35: 1 | E35: 9 | F35: 5 | G35: 1 | H35: 10 | I35: 8 | J35: -2 | K35: 8 | L35: 2 | M35: 5 | N35: 4 | O35: 55 | R35: PRD-032 | S35: 4 | T35: 1 | U35: 9 | V35: 5 | W35: 1 | X35: 10 | Y35: 8 | Z35: -2 | AA35: 8 | AB35: 2 | AC35: 5 | AD35: 4 | AE35: =AVERAGE(S35:AD35) -> 4.5833333 | AF35: =_xlfn.STDEV.P(S35:AD35) -> 3.5227436 | AG35: =AF35/AE35 -> 0.7685986 | AH35: =IF(AG35>0.6, "High",IF(AG35>0.3, "Moderate","Stable")) -> High | AI35: =_xlfn.XLOOKUP(R35,Table1[SKU_Code],Table1[Category],"Missing") -> Outerwear | AJ35: =SLOPE(Table17[[#This Row],[Jan]:[Dec]], {1,2,3,4,5,6,7,8,9,10,11,12}) -> -0.031468531 | AK35: =IF(Table17[[#This Row],[Slope]]>5,"Growing", IF(Table17[[#This Row],[Slope]]<-5,"Declining","Flat")) -> Flat
B36: PRD-033 | C36: 5 | D36: 2 | E36: 1 | F36: 3 | G36: 3 | H36: 11 | I36: 2 | M36: 8 | N36: 12 | O36: 47 | R36: PRD-033 | S36: 5 | T36: 2 | U36: 1 | V36: 3 | W36: 3 | X36: 11 | Y36: 2 | AC36: 8 | AD36: 12 | AE36: =AVERAGE(S36:AD36) -> 5.2222222 | AF36: =_xlfn.STDEV.P(S36:AD36) -> 3.8809443 | AG36: =AF36/AE36 -> 0.74315954 | AH36: =IF(AG36>0.6, "High",IF(AG36>0.3, "Moderate","Stable")) -> High | AI36: =_xlfn.XLOOKUP(R36,Table1[SKU_Code],Table1[Category],"Missing") -> Knitwear | AJ36: =SLOPE(Table17[[#This Row],[Jan]:[Dec]], {1,2,3,4,5,6,7,8,9,10,11,12}) -> 0.72988506 | AK36: =IF(Table17[[#This Row],[Slope]]>5,"Growing", IF(Table17[[#This Row],[Slope]]<-5,"Declining","Flat")) -> Flat
B37: PRD-034 | D37: 2 | E37: 9 | F37: 9 | G37: 3 | I37: 3 | J37: 2 | K37: 3 | L37: 1 | M37: 2 | N37: 16 | O37: 50 | R37: PRD-034 | T37: 2 | U37: 9 | V37: 9 | W37: 3 | Y37: 3 | Z37: 2 | AA37: 3 | AB37: 1 | AC37: 2 | AD37: 16 | AE37: =AVERAGE(S37:AD37) -> 5 | AF37: =_xlfn.STDEV.P(S37:AD37) -> 4.5607017 | AG37: =AF37/AE37 -> 0.91214034 | AH37: =IF(AG37>0.6, "High",IF(AG37>0.3, "Moderate","Stable")) -> High | AI37: =_xlfn.XLOOKUP(R37,Table1[SKU_Code],Table1[Category],"Missing") -> Pyjamas | AJ37: =SLOPE(Table17[[#This Row],[Jan]:[Dec]], {1,2,3,4,5,6,7,8,9,10,11,12}) -> 0.13774105 | AK37: =IF(Table17[[#This Row],[Slope]]>5,"Growing", IF(Table17[[#This Row],[Slope]]<-5,"Declining","Flat")) -> Flat
B38: PRD-035 | C38: 2 | D38: 7 | E38: 16 | F38: 3 | G38: 2 | H38: 5 | I38: 7 | J38: 1 | K38: 6 | L38: 9 | M38: 2 | N38: 4 | O38: 64 | R38: PRD-035 | S38: 2 | T38: 7 | U38: 16 | V38: 3 | W38: 2 | X38: 5 | Y38: 7 | Z38: 1 | AA38: 6 | AB38: 9 | AC38: 2 | AD38: 4 | AE38: =AVERAGE(S38:AD38) -> 5.3333333 | AF38: =_xlfn.STDEV.P(S38:AD38) -> 4.0069384 | AG38: =AF38/AE38 -> 0.75130096 | AH38: =IF(AG38>0.6, "High",IF(AG38>0.3, "Moderate","Stable")) -> High | AI38: =_xlfn.XLOOKUP(R38,Table1[SKU_Code],Table1[Category],"Missing") -> Basics | AJ38: =SLOPE(Table17[[#This Row],[Jan]:[Dec]], {1,2,3,4,5,6,7,8,9,10,11,12}) -> -0.2027972 | AK38: =IF(Table17[[#This Row],[Slope]]>5,"Growing", IF(Table17[[#This Row],[Slope]]<-5,"Declining","Flat")) -> Flat
B39: PRD-036 | C39: 6 | E39: 8 | F39: 5 | G39: 1 | H39: 1 | I39: 3 | J39: 5 | K39: 10 | L39: 5 | M39: 5 | N39: 9 | O39: 58 | R39: PRD-036 | S39: 6 | U39: 8 | V39: 5 | W39: 1 | X39: 1 | Y39: 3 | Z39: 5 | AA39: 10 | AB39: 5 | AC39: 5 | AD39: 9 | AE39: =AVERAGE(S39:AD39) -> 5.2727273 | AF39: =_xlfn.STDEV.P(S39:AD39) -> 2.7990553 | AG39: =AF39/AE39 -> 0.53085532 | AH39: =IF(AG39>0.6, "High",IF(AG39>0.3, "Moderate","Stable")) -> Moderate | AI39: =_xlfn.XLOOKUP(R39,Table1[SKU_Code],Table1[Category],"Missing") -> Basics | AJ39: =SLOPE(Table17[[#This Row],[Jan]:[Dec]], {1,2,3,4,5,6,7,8,9,10,11,12}) -> 0.20075188 | AK39: =IF(Table17[[#This Row],[Slope]]>5,"Growing", IF(Table17[[#This Row],[Slope]]<-5,"Declining","Flat")) -> Flat
B40: PRD-037 | C40: 1 | E40: 8 | F40: 7 | G40: 1 | H40: 11 | I40: 1 | J40: 14 | K40: 3 | L40: 5 | M40: 10 | N40: 10 | O40: 71 | R40: PRD-037 | S40: 1 | U40: 8 | V40: 7 | W40: 1 | X40: 11 | Y40: 1 | Z40: 14 | AA40: 3 | AB40: 5 | AC40: 10 | AD40: 10 | AE40: =AVERAGE(S40:AD40) -> 6.4545455 | AF40: =_xlfn.STDEV.P(S40:AD40) -> 4.356054 | AG40: =AF40/AE40 -> 0.67488161 | AH40: =IF(AG40>0.6, "High",IF(AG40>0.3, "Moderate","Stable")) -> High | AI40: =_xlfn.XLOOKUP(R40,Table1[SKU_Code],Table1[Category],"Missing") -> Basics | AJ40: =SLOPE(Table17[[#This Row],[Jan]:[Dec]], {1,2,3,4,5,6,7,8,9,10,11,12}) -> 0.49172932 | AK40: =IF(Table17[[#This Row],[Slope]]>5,"Growing", IF(Table17[[#This Row],[Slope]]<-5,"Declining","Flat")) -> Flat
B41: PRD-038 | C41: -2 | D41: 3 | E41: 6 | F41: 3 | H41: 10 | I41: 7 | J41: 3 | K41: 2 | L41: 2 | M41: 4 | N41: 3 | O41: 41 | R41: PRD-038 | S41: -2 | T41: 3 | U41: 6 | V41: 3 | X41: 10 | Y41: 7 | Z41: 3 | AA41: 2 | AB41: 2 | AC41: 4 | AD41: 3 | AE41: =AVERAGE(S41:AD41) -> 3.7272727 | AF41: =_xlfn.STDEV.P(S41:AD41) -> 2.956992 | AG41: =AF41/AE41 -> 0.79333932 | AH41: =IF(AG41>0.6, "High",IF(AG41>0.3, "Moderate","Stable")) -> High | AI41: =_xlfn.XLOOKUP(R41,Table1[SKU_Code],Table1[Category],"Missing") -> Dresses | AJ41: =SLOPE(Table17[[#This Row],[Jan]:[Dec]], {1,2,3,4,5,6,7,8,9,10,11,12}) -> 0.091849935 | AK41: =IF(Table17[[#This Row],[Slope]]>5,"Growing", IF(Table17[[#This Row],[Slope]]<-5,"Declining","Flat")) -> Flat
B42: PRD-039 | C42: 10 | D42: 2 | E42: 6 | F42: 3 | G42: 2 | H42: 4 | I42: 6 | K42: 2 | L42: 6 | M42: 5 | N42: 7 | O42: 53 | R42: PRD-039 | S42: 10 | T42: 2 | U42: 6 | V42: 3 | W42: 2 | X42: 4 | Y42: 6 | AA42: 2 | AB42: 6 | AC42: 5 | AD42: 7 | AE42: =AVERAGE(S42:AD42) -> 4.8181818 | AF42: =_xlfn.STDEV.P(S42:AD42) -> 2.4052285 | AG42: =AF42/AE42 -> 0.49919836 | AH42: =IF(AG42>0.6, "High",IF(AG42>0.3, "Moderate","Stable")) -> Moderate | AI42: =_xlfn.XLOOKUP(R42,Table1[SKU_Code],Table1[Category],"Missing") -> Co-ord Sets | AJ42: =SLOPE(Table17[[#This Row],[Jan]:[Dec]], {1,2,3,4,5,6,7,8,9,10,11,12}) -> -0.0019404916 | AK42: =IF(Table17[[#This Row],[Slope]]>5,"Growing", IF(Table17[[#This Row],[Slope]]<-5,"Declining","Flat")) -> Flat
B43: PRD-040 | C43: 1 | D43: 2 | E43: 4 | G43: 8 | H43: 3 | I43: 4 | J43: 3 | K43: 4 | L43: 6 | M43: 2 | N43: 10 | O43: 47 | R43: PRD-040 | S43: 1 | T43: 2 | U43: 4 | W43: 8 | X43: 3 | Y43: 4 | Z43: 3 | AA43: 4 | AB43: 6 | AC43: 2 | AD43: 10 | AE43: =AVERAGE(S43:AD43) -> 4.2727273 | AF43: =_xlfn.STDEV.P(S43:AD43) -> 2.5968831 | AG43: =AF43/AE43 -> 0.60778114 | AH43: =IF(AG43>0.6, "High",IF(AG43>0.3, "Moderate","Stable")) -> High | AI43: =_xlfn.XLOOKUP(R43,Table1[SKU_Code],Table1[Category],"Missing") -> Bottoms | AJ43: =SLOPE(Table17[[#This Row],[Jan]:[Dec]], {1,2,3,4,5,6,7,8,9,10,11,12}) -> 0.35847797 | AK43: =IF(Table17[[#This Row],[Slope]]>5,"Growing", IF(Table17[[#This Row],[Slope]]<-5,"Declining","Flat")) -> Flat
B44: Grand Total | C44: 138 | D44: 124 | E44: 302 | F44: 149 | G44: 125 | H44: 171 | I44: 189 | J44: 110 | K44: 218 | L44: 188 | M44: 239 | N44: 248 | O44: 2201

Sheet Inventory Analysis
A1: SKU_Code | B1: Product_Name | C1: Category | D1: Avg_Monthly_Demand | E1: Std Dev | F1: Avg_Daily_Demand | G1: Lead_Time_Days | H1: Safety_Stock | I1: ROP | J1: Units_On_Hand | K1: Reorder_Lvl | L1: Days_of_Supply | M1: Stock_Status
A2: PRD-001 | B2: =_xlfn.XLOOKUP(A2,Table1[SKU_Code],Table1[Product_Name],"Missing") -> Beige Co-ord Set | C2: =_xlfn.XLOOKUP(A2,Table1[SKU_Code],Table1[Category],"Missing") -> Co-ord Sets | D2: =_xlfn.XLOOKUP(A2,Table17[Row Labels],Table17[Average Monthly Qty],"Missing") -> 3.7272727 | E2: =_xlfn.XLOOKUP(A2,Table17[Row Labels],Table17[Std Dev],"Missing") -> 2.489648 | F2: =IF(D2="Missing","Missing",ROUND(D2/30,2)) -> 0.12 | G2: 14 | H2: =ROUND(1.65*E2*SQRT(G2/30),0) -> 3 | I2: =ROUND((F2*G2)+H2,0) -> 5 | J2: =_xlfn.LET(_xlpm.x,_xlfn.XLOOKUP(A2,Table2[SKU_Code],Table2[Units_On_Hand],""),IF(_xlpm.x="","Missing",_xlpm.x)) -> 3 | K2: =_xlfn.LET(_xlpm.x,_xlfn.XLOOKUP(A2,Table2[SKU_Code],Table2[Reorder_Lvl],""),IF(_xlpm.x="","Missing",_xlpm.x)) -> 8 | L2: =IF(OR(J2="Missing",F2=0),"Missing",ROUND(J2/F2,0)) -> 25 | M2: =IF(J2="Missing","Missing",IF(J2<I2,"Reorder Now","OK")) -> Reorder Now
A3: PRD-002 | B3: =_xlfn.XLOOKUP(A3,Table1[SKU_Code],Table1[Product_Name],"Missing") -> Beige Co-ord Set | C3: =_xlfn.XLOOKUP(A3,Table1[SKU_Code],Table1[Category],"Missing") -> Co-ord Sets | D3: =_xlfn.XLOOKUP(A3,Table17[Row Labels],Table17[Average Monthly Qty],"Missing") -> 5.75 | E3: =_xlfn.XLOOKUP(A3,Table17[Row Labels],Table17[Std Dev],"Missing") -> 4.1857895 | F3: =IF(D3="Missing","Missing",ROUND(D3/30,2)) -> 0.19 | G3: 14 | H3: =ROUND(1.65*E3*SQRT(G3/30),0) -> 5 | I3: =ROUND((F3*G3)+H3,0) -> 8 | J3: =_xlfn.LET(_xlpm.x,_xlfn.XLOOKUP(A3,Table2[SKU_Code],Table2[Units_On_Hand],""),IF(_xlpm.x="","Missing",_xlpm.x)) -> 23 | K3: =_xlfn.LET(_xlpm.x,_xlfn.XLOOKUP(A3,Table2[SKU_Code],Table2[Reorder_Lvl],""),IF(_xlpm.x="","Missing",_xlpm.x)) -> 5 | L3: =IF(OR(J3="Missing",F3=0),"Missing",ROUND(J3/F3,0)) -> 121 | M3: =IF(J3="Missing","Missing",IF(J3<I3,"Reorder Now","OK")) -> OK
A4: PRD-003 | B4: =_xlfn.XLOOKUP(A4,Table1[SKU_Code],Table1[Product_Name],"Missing") -> Beige Co-ord Set | C4: =_xlfn.XLOOKUP(A4,Table1[SKU_Code],Table1[Category],"Missing") -> Co-ord Sets | D4: =_xlfn.XLOOKUP(A4,Table17[Row Labels],Table17[Average Monthly Qty],"Missing") -> 5.6363636 | E4: =_xlfn.XLOOKUP(A4,Table17[Row Labels],Table17[Std Dev],"Missing") -> 3.7239453 | F4: =IF(D4="Missing","Missing",ROUND(D4/30,2)) -> 0.19 | G4: 14 | H4: =ROUND(1.65*E4*SQRT(G4/30),0) -> 4 | I4: =ROUND((F4*G4)+H4,0) -> 7 | J4: =_xlfn.LET(_xlpm.x,_xlfn.XLOOKUP(A4,Table2[SKU_Code],Table2[Units_On_Hand],""),IF(_xlpm.x="","Missing",_xlpm.x)) -> 4 | K4: =_xlfn.LET(_xlpm.x,_xlfn.XLOOKUP(A4,Table2[SKU_Code],Table2[Reorder_Lvl],""),IF(_xlpm.x="","Missing",_xlpm.x)) -> 10 | L4: =IF(OR(J4="Missing",F4=0),"Missing",ROUND(J4/F4,0)) -> 21 | M4: =IF(J4="Missing","Missing",IF(J4<I4,"Reorder Now","OK")) -> Reorder Now
A5: PRD-004 | B5: =_xlfn.XLOOKUP(A5,Table1[SKU_Code],Table1[Product_Name],"Missing") -> Pink Sweatshirt | C5: =_xlfn.XLOOKUP(A5,Table1[SKU_Code],Table1[Category],"Missing") -> Sweatshirts | D5: =_xlfn.XLOOKUP(A5,Table17[Row Labels],Table17[Average Monthly Qty],"Missing") -> 5.7272727 | E5: =_xlfn.XLOOKUP(A5,Table17[Row Labels],Table17[Std Dev],"Missing") -> 3.2218264 | F5: =IF(D5="Missing","Missing",ROUND(D5/30,2)) -> 0.19 | G5: 14 | H5: =ROUND(1.65*E5*SQRT(G5/30),0) -> 4 | I5: =ROUND((F5*G5)+H5,0) -> 7 | J5: =_xlfn.LET(_xlpm.x,_xlfn.XLOOKUP(A5,Table2[SKU_Code],Table2[Units_On_Hand],""),IF(_xlpm.x="","Missing",_xlpm.x)) -> 13 | K5: =_xlfn.LET(_xlpm.x,_xlfn.XLOOKUP(A5,Table2[SKU_Code],Table2[Reorder_Lvl],""),IF(_xlpm.x="","Missing",_xlpm.x)) -> 8 | L5: =IF(OR(J5="Missing",F5=0),"Missing",ROUND(J5/F5,0)) -> 68 | M5: =IF(J5="Missing","Missing",IF(J5<I5,"Reorder Now","OK")) -> OK
A6: PRD-005 | B6: =_xlfn.XLOOKUP(A6,Table1[SKU_Code],Table1[Product_Name],"Missing") -> Pink Sweatshirt | C6: =_xlfn.XLOOKUP(A6,Table1[SKU_Code],Table1[Category],"Missing") -> Sweatshirts | D6: =_xlfn.XLOOKUP(A6,Table17[Row Labels],Table17[Average Monthly Qty],"Missing") -> 6.8 | E6: =_xlfn.XLOOKUP(A6,Table17[Row Labels],Table17[Std Dev],"Missing") -> 4.1665333 | F6: =IF(D6="Missing","Missing",ROUND(D6/30,2)) -> 0.23 | G6: 14 | H6: =ROUND(1.65*E6*SQRT(G6/30),0) -> 5 | I6: =ROUND((F6*G6)+H6,0) -> 8 | J6: =_xlfn.LET(_xlpm.x,_xlfn.XLOOKUP(A6,Table2[SKU_Code],Table2[Units_On_Hand],""),IF(_xlpm.x="","Missing",_xlpm.x)) -> 22 | K6: =_xlfn.LET(_xlpm.x,_xlfn.XLOOKUP(A6,Table2[SKU_Code],Table2[Reorder_Lvl],""),IF(_xlpm.x="","Missing",_xlpm.x)) -> 11 | L6: =IF(OR(J6="Missing",F6=0),"Missing",ROUND(J6/F6,0)) -> 96 | M6: =IF(J6="Missing","Missing",IF(J6<I6,"Reorder Now","OK")) -> OK
A7: PRD-006 | B7: =_xlfn.XLOOKUP(A7,Table1[SKU_Code],Table1[Product_Name],"Missing") -> Pink Sweatshirt | C7: =_xlfn.XLOOKUP(A7,Table1[SKU_Code],Table1[Category],"Missing") -> Sweatshirts | D7: =_xlfn.XLOOKUP(A7,Table17[Row Labels],Table17[Average Monthly Qty],"Missing") -> 4.9166667 | E7: =_xlfn.XLOOKUP(A7,Table17[Row Labels],Table17[Std Dev],"Missing") -> 3.8613109 | F7: =IF(D7="Missing","Missing",ROUND(D7/30,2)) -> 0.16 | G7: 14 | H7: =ROUND(1.65*E7*SQRT(G7/30),0) -> 4 | I7: =ROUND((F7*G7)+H7,0) -> 6 | J7: =_xlfn.LET(_xlpm.x,_xlfn.XLOOKUP(A7,Table2[SKU_Code],Table2[Units_On_Hand],""),IF(_xlpm.x="","Missing",_xlpm.x)) -> 40 | K7: =_xlfn.LET(_xlpm.x,_xlfn.XLOOKUP(A7,Table2[SKU_Code],Table2[Reorder_Lvl],""),IF(_xlpm.x="","Missing",_xlpm.x)) -> 10 | L7: =IF(OR(J7="Missing",F7=0),"Missing",ROUND(J7/F7,0)) -> 250 | M7: =IF(J7="Missing","Missing",IF(J7<I7,"Reorder Now","OK")) -> OK
A8: PRD-007 | B8: =_xlfn.XLOOKUP(A8,Table1[SKU_Code],Table1[Product_Name],"Missing") -> Olive Sweatshirt | C8: =_xlfn.XLOOKUP(A8,Table1[SKU_Code],Table1[Category],"Missing") -> Sweatshirts | D8: =_xlfn.XLOOKUP(A8,Table17[Row Labels],Table17[Average Monthly Qty],"Missing") -> 5.2727273 | E8: =_xlfn.XLOOKUP(A8,Table17[Row Labels],Table17[Std Dev],"Missing") -> 3.1069105 | F8: =IF(D8="Missing","Missing",ROUND(D8/30,2)) -> 0.18 | G8: 14 | H8: =ROUND(1.65*E8*SQRT(G8/30),0) -> 4 | I8: =ROUND((F8*G8)+H8,0) -> 7 | J8: =_xlfn.LET(_xlpm.x,_xlfn.XLOOKUP(A8,Table2[SKU_Code],Table2[Units_On_Hand],""),IF(_xlpm.x="","Missing",_xlpm.x)) -> 9 | K8: =_xlfn.LET(_xlpm.x,_xlfn.XLOOKUP(A8,Table2[SKU_Code],Table2[Reorder_Lvl],""),IF(_xlpm.x="","Missing",_xlpm.x)) -> 11 | L8: =IF(OR(J8="Missing",F8=0),"Missing",ROUND(J8/F8,0)) -> 50 | M8: =IF(J8="Missing","Missing",IF(J8<I8,"Reorder Now","OK")) -> OK
A9: PRD-008 | B9: =_xlfn.XLOOKUP(A9,Table1[SKU_Code],Table1[Product_Name],"Missing") -> Olive Sweatshirt | C9: =_xlfn.XLOOKUP(A9,Table1[SKU_Code],Table1[Category],"Missing") -> Sweatshirts | D9: =_xlfn.XLOOKUP(A9,Table17[Row Labels],Table17[Average Monthly Qty],"Missing") -> 6.7272727 | E9: =_xlfn.XLOOKUP(A9,Table17[Row Labels],Table17[Std Dev],"Missing") -> 4.8820806 | F9: =IF(D9="Missing","Missing",ROUND(D9/30,2)) -> 0.22 | G9: 14 | H9: =ROUND(1.65*E9*SQRT(G9/30),0) -> 6 | I9: =ROUND((F9*G9)+H9,0) -> 9 | J9: =_xlfn.LET(_xlpm.x,_xlfn.XLOOKUP(A9,Table2[SKU_Code],Table2[Units_On_Hand],""),IF(_xlpm.x="","Missing",_xlpm.x)) -> Missing | K9: =_xlfn.LET(_xlpm.x,_xlfn.XLOOKUP(A9,Table2[SKU_Code],Table2[Reorder_Lvl],""),IF(_xlpm.x="","Missing",_xlpm.x)) -> 10 | L9: =IF(OR(J9="Missing",F9=0),"Missing",ROUND(J9/F9,0)) -> Missing | M9: =IF(J9="Missing","Missing",IF(J9<I9,"Reorder Now","OK")) -> Missing
A10: PRD-009 | B10: =_xlfn.XLOOKUP(A10,Table1[SKU_Code],Table1[Product_Name],"Missing") -> Red Sweatshirt | C10: =_xlfn.XLOOKUP(A10,Table1[SKU_Code],Table1[Category],"Missing") -> Sweatshirts | D10: =_xlfn.XLOOKUP(A10,Table17[Row Labels],Table17[Average Monthly Qty],"Missing") -> 6.4545455 | E10: =_xlfn.XLOOKUP(A10,Table17[Row Labels],Table17[Std Dev],"Missing") -> 3.4208887 | F10: =IF(D10="Missing","Missing",ROUND(D10/30,2)) -> 0.22 | G10: 14 | H10: =ROUND(1.65*E10*SQRT(G10/30),0) -> 4 | I10: =ROUND((F10*G10)+H10,0) -> 7 | J10: =_xlfn.LET(_xlpm.x,_xlfn.XLOOKUP(A10,Table2[SKU_Code],Table2[Units_On_Hand],""),IF(_xlpm.x="","Missing",_xlpm.x)) -> 2 | K10: =_xlfn.LET(_xlpm.x,_xlfn.XLOOKUP(A10,Table2[SKU_Code],Table2[Reorder_Lvl],""),IF(_xlpm.x="","Missing",_xlpm.x)) -> 7 | L10: =IF(OR(J10="Missing",F10=0),"Missing",ROUND(J10/F10,0)) -> 9 | M10: =IF(J10="Missing","Missing",IF(J10<I10,"Reorder Now","OK")) -> Reorder Now
A11: PRD-010 | B11: =_xlfn.XLOOKUP(A11,Table1[SKU_Code],Table1[Product_Name],"Missing") -> Blue Sweatshirt | C11: =_xlfn.XLOOKUP(A11,Table1[SKU_Code],Table1[Category],"Missing") -> Sweatshirts | D11: =_xlfn.XLOOKUP(A11,Table17[Row Labels],Table17[Average Monthly Qty],"Missing") -> 3.6363636 | E11: =_xlfn.XLOOKUP(A11,Table17[Row Labels],Table17[Std Dev],"Missing") -> 2.3845231 | F11: =IF(D11="Missing","Missing",ROUND(D11/30,2)) -> 0.12 | G11: 14 | H11: =ROUND(1.65*E11*SQRT(G11/30),0) -> 3 | I11: =ROUND((F11*G11)+H11,0) -> 5 | J11: =_xlfn.LET(_xlpm.x,_xlfn.XLOOKUP(A11,Table2[SKU_Code],Table2[Units_On_Hand],""),IF(_xlpm.x="","Missing",_xlpm.x)) -> 10 | K11: =_xlfn.LET(_xlpm.x,_xlfn.XLOOKUP(A11,Table2[SKU_Code],Table2[Reorder_Lvl],""),IF(_xlpm.x="","Missing",_xlpm.x)) -> 8 | L11: =IF(OR(J11="Missing",F11=0),"Missing",ROUND(J11/F11,0)) -> 83 | M11: =IF(J11="Missing","Missing",IF(J11<I11,"Reorder Now","OK")) -> OK
A12: PRD-011 | B12: =_xlfn.XLOOKUP(A12,Table1[SKU_Code],Table1[Product_Name],"Missing") -> Burgundy Knit Dress | C12: =_xlfn.XLOOKUP(A12,Table1[SKU_Code],Table1[Category],"Missing") -> Knit Dresses | D12: =_xlfn.XLOOKUP(A12,Table17[Row Labels],Table17[Average Monthly Qty],"Missing") -> 3.8 | E12: =_xlfn.XLOOKUP(A12,Table17[Row Labels],Table17[Std Dev],"Missing") -> 3.4292856 | F12: =IF(D12="Missing","Missing",ROUND(D12/30,2)) -> 0.13 | G12: 14 | H12: =ROUND(1.65*E12*SQRT(G12/30),0) -> 4 | I12: =ROUND((F12*G12)+H12,0) -> 6 | J12: =_xlfn.LET(_xlpm.x,_xlfn.XLOOKUP(A12,Table2[SKU_Code],Table2[Units_On_Hand],""),IF(_xlpm.x="","Missing",_xlpm.x)) -> 35 | K12: =_xlfn.LET(_xlpm.x,_xlfn.XLOOKUP(A12,Table2[SKU_Code],Table2[Reorder_Lvl],""),IF(_xlpm.x="","Missing",_xlpm.x)) -> 16 | L12: =IF(OR(J12="Missing",F12=0),"Missing",ROUND(J12/F12,0)) -> 269 | M12: =IF(J12="Missing","Missing",IF(J12<I12,"Reorder Now","OK")) -> OK
A13: PRD-012 | B13: =_xlfn.XLOOKUP(A13,Table1[SKU_Code],Table1[Product_Name],"Missing") -> Burgundy Knit Dress | C13: =_xlfn.XLOOKUP(A13,Table1[SKU_Code],Table1[Category],"Missing") -> Knit Dresses | D13: =_xlfn.XLOOKUP(A13,Table17[Row Labels],Table17[Average Monthly Qty],"Missing") -> 4.2 | E13: =_xlfn.XLOOKUP(A13,Table17[Row Labels],Table17[Std Dev],"Missing") -> 3.4583233 | F13: =IF(D13="Missing","Missing",ROUND(D13/30,2)) -> 0.14 | G13: 14 | H13: =ROUND(1.65*E13*SQRT(G13/30),0) -> 4 | I13: =ROUND((F13*G13)+H13,0) -> 6 | J13: =_xlfn.LET(_xlpm.x,_xlfn.XLOOKUP(A13,Table2[SKU_Code],Table2[Units_On_Hand],""),IF(_xlpm.x="","Missing",_xlpm.x)) -> 16 | K13: =_xlfn.LET(_xlpm.x,_xlfn.XLOOKUP(A13,Table2[SKU_Code],Table2[Reorder_Lvl],""),IF(_xlpm.x="","Missing",_xlpm.x)) -> 13 | L13: =IF(OR(J13="Missing",F13=0),"Missing",ROUND(J13/F13,0)) -> 114 | M13: =IF(J13="Missing","Missing",IF(J13<I13,"Reorder Now","OK")) -> OK
... A41: PRD-040 | B41: =_xlfn.XLOOKUP(A41,Table1[SKU_Code],Table1[Product_Name],"Missing") -> Navy Wide Leg Pants | C41: =_xlfn.XLOOKUP(A41,Table1[SKU_Code],Table1[Category],"Missing") -> Bottoms | D41: =_xlfn.XLOOKUP(A41,Table17[Row Labels],Table17[Average Monthly Qty],"Missing") -> 4.2727273 | E41: =_xlfn.XLOOKUP(A41,Table17[Row Labels],Table17[Std Dev],"Missing") -> 2.5968831 | F41: =IF(D41="Missing","Missing",ROUND(D41/30,2)) -> 0.14 | G41: 14 | H41: =ROUND(1.65*E41*SQRT(G41/30),0) -> 3 | I41: =ROUND((F41*G41)+H41,0) -> 5 | J41: =_xlfn.LET(_xlpm.x,_xlfn.XLOOKUP(A41,Table2[SKU_Code],Table2[Units_On_Hand],""),IF(_xlpm.x="","Missing",_xlpm.x)) -> 30 | K41: =_xlfn.LET(_xlpm.x,_xlfn.XLOOKUP(A41,Table2[SKU_Code],Table2[Reorder_Lvl],""),IF(_xlpm.x="","Missing",_xlpm.x)) -> 20 | L41: =IF(OR(J41="Missing",F41=0),"Missing",ROUND(J41/F41,0)) -> 214 | M41: =IF(J41="Missing","Missing",IF(J41<I41,"Reorder Now","OK")) -> OK

Sheet Financial Analysis
A1: SKU_Code | B1: Product_Name | C1: Units_Received | D1: Units_Sold | E1: Sell_Through_Rate | F1: Cost_Price | G1: Selling_Price | H1: Gross_Margin_Pct | I1: Total_Revenue | J1: Revenue_Rank | K1: Cumulative_Revenue_Pct | L1: ABC_Class | M1: Gross_Margin_Dollar | N1: Inventory_Investment | O1: GMROI | P1: GMROI_Class
A2: PRD-001 | B2: Beige Co-ord Set | C2: =IFERROR(_xlfn.XLOOKUP(A2,Table2[SKU_Code],Table2[Received_Qty]),"Missing") -> 82 | D2: =IFERROR(SUMIF(Table4[SKU_Code], A2, Table4[Qty]), "Missing") -> 41 | E2: =IFERROR(D2/C2,"Missing") -> 0.5 | F2: =IFERROR(_xlfn.XLOOKUP(A2, Table1[SKU_Code], Table1[Cost_IRR]), "Missing") -> 185000 | G2: =IFERROR(_xlfn.XLOOKUP(A2,Table1[SKU_Code],Table1[RRP_IRR]),"Missing") -> 420000 | H2: =IFERROR((G2-F2)/G2, "Missing") -> 0.55952381 | I2: =SUMIF(Table4[SKU_Code],'Financial Analysis'!A2,Table4[Revenue]) -> 16590000 | J2: =_xlfn.RANK.EQ(I2,$I$2:$I$41,0) -> 12 | K2: =SUMIF($J$2:$J$41,"<="&J2,$I$2:$I$41)/SUM($I$2:$I$41) -> 0.47056008 | L2: =IF(K2<=0.7,"A",IF(K2<=0.9,"B","C")) -> A | M2: =I2-(D2*F2) -> 9005000 | N2: =C2*F2 -> 15170000 | O2: =IFERROR(ROUND(M2/N2,2),"Missing") -> 0.59 | P2: =IF(O2>=2,"A",IF(O2>=1,"B","C")) -> C
A3: PRD-002 | B3: Beige Co-ord Set | C3: =IFERROR(_xlfn.XLOOKUP(A3,Table2[SKU_Code],Table2[Received_Qty]),"Missing") -> 134 | D3: =IFERROR(SUMIF(Table4[SKU_Code], A3, Table4[Qty]), "Missing") -> 69 | E3: =IFERROR(D3/C3,"Missing") -> 0.51492537 | F3: =IFERROR(_xlfn.XLOOKUP(A3, Table1[SKU_Code], Table1[Cost_IRR]), "Missing") -> 185000 | G3: =IFERROR(_xlfn.XLOOKUP(A3,Table1[SKU_Code],Table1[RRP_IRR]),"Missing") -> 420000 | H3: =IFERROR((G3-F3)/G3, "Missing") -> 0.55952381 | I3: =SUMIF(Table4[SKU_Code],'Financial Analysis'!A3,Table4[Revenue]) -> 28098000 | J3: =_xlfn.RANK.EQ(I3,$I$2:$I$41,0) -> 4 | K3: =SUMIF($J$2:$J$41,"<="&J3,$I$2:$I$41)/SUM($I$2:$I$41) -> 0.19482561 | L3: =IF(K3<=0.7,"A",IF(K3<=0.9,"B","C")) -> A | M3: =I3-(D3*F3) -> 15333000 | N3: =C3*F3 -> 24790000 | O3: =IFERROR(ROUND(M3/N3,2),"Missing") -> 0.62 | P3: =IF(O3>=2,"A",IF(O3>=1,"B","C")) -> C
A4: PRD-003 | B4: Beige Co-ord Set | C4: =IFERROR(_xlfn.XLOOKUP(A4,Table2[SKU_Code],Table2[Received_Qty]),"Missing") -> 33 | D4: =IFERROR(SUMIF(Table4[SKU_Code], A4, Table4[Qty]), "Missing") -> 62 | E4: =IFERROR(D4/C4,"Missing") -> 1.8787879 | F4: =IFERROR(_xlfn.XLOOKUP(A4, Table1[SKU_Code], Table1[Cost_IRR]), "Missing") -> 185000 | G4: =IFERROR(_xlfn.XLOOKUP(A4,Table1[SKU_Code],Table1[RRP_IRR]),"Missing") -> 420000 | H4: =IFERROR((G4-F4)/G4, "Missing") -> 0.55952381 | I4: =SUMIF(Table4[SKU_Code],'Financial Analysis'!A4,Table4[Revenue]) -> 24990000 | J4: =_xlfn.RANK.EQ(I4,$I$2:$I$41,0) -> 5 | K4: =SUMIF($J$2:$J$41,"<="&J4,$I$2:$I$41)/SUM($I$2:$I$41) -> 0.23691656 | L4: =IF(K4<=0.7,"A",IF(K4<=0.9,"B","C")) -> A | M4: =I4-(D4*F4) -> 13520000 | N4: =C4*F4 -> 6105000 | O4: =IFERROR(ROUND(M4/N4,2),"Missing") -> 2.21 | P4: =IF(O4>=2,"A",IF(O4>=1,"B","C")) -> A
A5: PRD-004 | B5: Pink Sweatshirt | C5: =IFERROR(_xlfn.XLOOKUP(A5,Table2[SKU_Code],Table2[Received_Qty]),"Missing") -> 39 | D5: =IFERROR(SUMIF(Table4[SKU_Code], A5, Table4[Qty]), "Missing") -> 63 | E5: =IFERROR(D5/C5,"Missing") -> 1.6153846 | F5: =IFERROR(_xlfn.XLOOKUP(A5, Table1[SKU_Code], Table1[Cost_IRR]), "Missing") -> 95000 | G5: =IFERROR(_xlfn.XLOOKUP(A5,Table1[SKU_Code],Table1[RRP_IRR]),"Missing") -> 220000 | H5: =IFERROR((G5-F5)/G5, "Missing") -> 0.56818182 | I5: =SUMIF(Table4[SKU_Code],'Financial Analysis'!A5,Table4[Revenue]) -> 13585000 | J5: =_xlfn.RANK.EQ(I5,$I$2:$I$41,0) -> 19 | K5: =SUMIF($J$2:$J$41,"<="&J5,$I$2:$I$41)/SUM($I$2:$I$41) -> 0.64268285 | L5: =IF(K5<=0.7,"A",IF(K5<=0.9,"B","C")) -> A | M5: =I5-(D5*F5) -> 7600000 | N5: =C5*F5 -> 3705000 | O5: =IFERROR(ROUND(M5/N5,2),"Missing") -> 2.05 | P5: =IF(O5>=2,"A",IF(O5>=1,"B","C")) -> A | S5: Revenue ABC | T5: GMROI Class
A6: PRD-005 | B6: Pink Sweatshirt | C6: =IFERROR(_xlfn.XLOOKUP(A6,Table2[SKU_Code],Table2[Received_Qty]),"Missing") -> 51 | D6: =IFERROR(SUMIF(Table4[SKU_Code], A6, Table4[Qty]), "Missing") -> 68 | E6: =IFERROR(D6/C6,"Missing") -> 1.3333333 | F6: =IFERROR(_xlfn.XLOOKUP(A6, Table1[SKU_Code], Table1[Cost_IRR]), "Missing") -> 95000 | G6: =IFERROR(_xlfn.XLOOKUP(A6,Table1[SKU_Code],Table1[RRP_IRR]),"Missing") -> 220000 | H6: =IFERROR((G6-F6)/G6, "Missing") -> 0.56818182 | I6: =SUMIF(Table4[SKU_Code],'Financial Analysis'!A6,Table4[Revenue]) -> 14256000 | J6: =_xlfn.RANK.EQ(I6,$I$2:$I$41,0) -> 16 | K6: =SUMIF($J$2:$J$41,"<="&J6,$I$2:$I$41)/SUM($I$2:$I$41) -> 0.57271865 | L6: =IF(K6<=0.7,"A",IF(K6<=0.9,"B","C")) -> A | M6: =I6-(D6*F6) -> 7796000 | N6: =C6*F6 -> 4845000 | O6: =IFERROR(ROUND(M6/N6,2),"Missing") -> 1.61 | P6: =IF(O6>=2,"A",IF(O6>=1,"B","C")) -> B | R6: Class A | S6: 20 | T6: 5
A7: PRD-006 | B7: Pink Sweatshirt | C7: =IFERROR(_xlfn.XLOOKUP(A7,Table2[SKU_Code],Table2[Received_Qty]),"Missing") -> 146 | D7: =IFERROR(SUMIF(Table4[SKU_Code], A7, Table4[Qty]), "Missing") -> 59 | E7: =IFERROR(D7/C7,"Missing") -> 0.40410959 | F7: =IFERROR(_xlfn.XLOOKUP(A7, Table1[SKU_Code], Table1[Cost_IRR]), "Missing") -> 95000 | G7: =IFERROR(_xlfn.XLOOKUP(A7,Table1[SKU_Code],Table1[RRP_IRR]),"Missing") -> 220000 | H7: =IFERROR((G7-F7)/G7, "Missing") -> 0.56818182 | I7: =SUMIF(Table4[SKU_Code],'Financial Analysis'!A7,Table4[Revenue]) -> 12672000 | J7: =_xlfn.RANK.EQ(I7,$I$2:$I$41,0) -> 22 | K7: =SUMIF($J$2:$J$41,"<="&J7,$I$2:$I$41)/SUM($I$2:$I$41) -> 0.70886494 | L7: =IF(K7<=0.7,"A",IF(K7<=0.9,"B","C")) -> B | M7: =I7-(D7*F7) -> 7067000 | N7: =C7*F7 -> 13870000 | O7: =IFERROR(ROUND(M7/N7,2),"Missing") -> 0.51 | P7: =IF(O7>=2,"A",IF(O7>=1,"B","C")) -> C | R7: Class B | S7: 12 | T7: 13
A8: PRD-007 | B8: Olive Sweatshirt | C8: =IFERROR(_xlfn.XLOOKUP(A8,Table2[SKU_Code],Table2[Received_Qty]),"Missing") -> 135 | D8: =IFERROR(SUMIF(Table4[SKU_Code], A8, Table4[Qty]), "Missing") -> 58 | E8: =IFERROR(D8/C8,"Missing") -> 0.42962963 | F8: =IFERROR(_xlfn.XLOOKUP(A8, Table1[SKU_Code], Table1[Cost_IRR]), "Missing") -> 95000 | G8: =IFERROR(_xlfn.XLOOKUP(A8,Table1[SKU_Code],Table1[RRP_IRR]),"Missing") -> 215000 | H8: =IFERROR((G8-F8)/G8, "Missing") -> 0.55813953 | I8: =SUMIF(Table4[SKU_Code],'Financial Analysis'!A8,Table4[Revenue]) -> 12018500 | J8: =_xlfn.RANK.EQ(I8,$I$2:$I$41,0) -> 24 | K8: =SUMIF($J$2:$J$41,"<="&J8,$I$2:$I$41)/SUM($I$2:$I$41) -> 0.75004131 | L8: =IF(K8<=0.7,"A",IF(K8<=0.9,"B","C")) -> B | M8: =I8-(D8*F8) -> 6508500 | N8: =C8*F8 -> 12825000 | O8: =IFERROR(ROUND(M8/N8,2),"Missing") -> 0.51 | P8: =IF(O8>=2,"A",IF(O8>=1,"B","C")) -> C | R8: Class C | S8: 8 | T8: 22
A9: PRD-008 | B9: Olive Sweatshirt | C9: =IFERROR(_xlfn.XLOOKUP(A9,Table2[SKU_Code],Table2[Received_Qty]),"Missing") -> 119 | D9: =IFERROR(SUMIF(Table4[SKU_Code], A9, Table4[Qty]), "Missing") -> 74 | E9: =IFERROR(D9/C9,"Missing") -> 0.62184874 | F9: =IFERROR(_xlfn.XLOOKUP(A9, Table1[SKU_Code], Table1[Cost_IRR]), "Missing") -> 95000 | G9: =IFERROR(_xlfn.XLOOKUP(A9,Table1[SKU_Code],Table1[RRP_IRR]),"Missing") -> 215000 | H9: =IFERROR((G9-F9)/G9, "Missing") -> 0.55813953 | I9: =SUMIF(Table4[SKU_Code],'Financial Analysis'!A9,Table4[Revenue]) -> 15544500 | J9: =_xlfn.RANK.EQ(I9,$I$2:$I$41,0) -> 14 | K9: =SUMIF($J$2:$J$41,"<="&J9,$I$2:$I$41)/SUM($I$2:$I$41) -> 0.52449596 | L9: =IF(K9<=0.7,"A",IF(K9<=0.9,"B","C")) -> A | M9: =I9-(D9*F9) -> 8514500 | N9: =C9*F9 -> 11305000 | O9: =IFERROR(ROUND(M9/N9,2),"Missing") -> 0.75 | P9: =IF(O9>=2,"A",IF(O9>=1,"B","C")) -> C
A10: PRD-009 | B10: Red Sweatshirt | C10: =IFERROR(_xlfn.XLOOKUP(A10,Table2[SKU_Code],Table2[Received_Qty]),"Missing") -> 58 | D10: =IFERROR(SUMIF(Table4[SKU_Code], A10, Table4[Qty]), "Missing") -> 71 | E10: =IFERROR(D10/C10,"Missing") -> 1.2241379 | F10: =IFERROR(_xlfn.XLOOKUP(A10, Table1[SKU_Code], Table1[Cost_IRR]), "Missing") -> 95000 | G10: =IFERROR(_xlfn.XLOOKUP(A10,Table1[SKU_Code],Table1[RRP_IRR]),"Missing") -> 210000 | H10: =IFERROR((G10-F10)/G10, "Missing") -> 0.54761905 | I10: =SUMIF(Table4[SKU_Code],'Financial Analysis'!A10,Table4[Revenue]) -> 14374500 | J10: =_xlfn.RANK.EQ(I10,$I$2:$I$41,0) -> 15 | K10: =SUMIF($J$2:$J$41,"<="&J10,$I$2:$I$41)/SUM($I$2:$I$41) -> 0.5487071 | L10: =IF(K10<=0.7,"A",IF(K10<=0.9,"B","C")) -> A | M10: =I10-(D10*F10) -> 7629500 | N10: =C10*F10 -> 5510000 | O10: =IFERROR(ROUND(M10/N10,2),"Missing") -> 1.38 | P10: =IF(O10>=2,"A",IF(O10>=1,"B","C")) -> B
A11: PRD-010 | B11: Blue Sweatshirt | C11: =IFERROR(_xlfn.XLOOKUP(A11,Table2[SKU_Code],Table2[Received_Qty]),"Missing") -> 95 | D11: =IFERROR(SUMIF(Table4[SKU_Code], A11, Table4[Qty]), "Missing") -> 40 | E11: =IFERROR(D11/C11,"Missing") -> 0.42105263 | F11: =IFERROR(_xlfn.XLOOKUP(A11, Table1[SKU_Code], Table1[Cost_IRR]), "Missing") -> 95000 | G11: =IFERROR(_xlfn.XLOOKUP(A11,Table1[SKU_Code],Table1[RRP_IRR]),"Missing") -> 210000 | H11: =IFERROR((G11-F11)/G11, "Missing") -> 0.54761905 | I11: =SUMIF(Table4[SKU_Code],'Financial Analysis'!A11,Table4[Revenue]) -> 8242500 | J11: =_xlfn.RANK.EQ(I11,$I$2:$I$41,0) -> 36 | K11: =SUMIF($J$2:$J$41,"<="&J11,$I$2:$I$41)/SUM($I$2:$I$41) -> 0.95301317 | L11: =IF(K11<=0.7,"A",IF(K11<=0.9,"B","C")) -> C | M11: =I11-(D11*F11) -> 4442500 | N11: =C11*F11 -> 9025000 | O11: =IFERROR(ROUND(M11/N11,2),"Missing") -> 0.49 | P11: =IF(O11>=2,"A",IF(O11>=1,"B","C")) -> C
A12: PRD-011 | B12: Burgundy Knit Dress | C12: =IFERROR(_xlfn.XLOOKUP(A12,Table2[SKU_Code],Table2[Received_Qty]),"Missing") -> 92 | D12: =IFERROR(SUMIF(Table4[SKU_Code], A12, Table4[Qty]), "Missing") -> 38 | E12: =IFERROR(D12/C12,"Missing") -> 0.41304348 | F12: =IFERROR(_xlfn.XLOOKUP(A12, Table1[SKU_Code], Table1[Cost_IRR]), "Missing") -> 140000 | G12: =IFERROR(_xlfn.XLOOKUP(A12,Table1[SKU_Code],Table1[RRP_IRR]),"Missing") -> 320000 | H12: =IFERROR((G12-F12)/G12, "Missing") -> 0.5625 | I12: =SUMIF(Table4[SKU_Code],'Financial Analysis'!A12,Table4[Revenue]) -> 11920000 | J12: =_xlfn.RANK.EQ(I12,$I$2:$I$41,0) -> 26 | K12: =SUMIF($J$2:$J$41,"<="&J12,$I$2:$I$41)/SUM($I$2:$I$41) -> 0.79028162 | L12: =IF(K12<=0.7,"A",IF(K12<=0.9,"B","C")) -> B | M12: =I12-(D12*F12) -> 6600000 | N12: =C12*F12 -> 12880000 | O12: =IFERROR(ROUND(M12/N12,2),"Missing") -> 0.51 | P12: =IF(O12>=2,"A",IF(O12>=1,"B","C")) -> C
A13: PRD-012 | B13: Burgundy Knit Dress | C13: =IFERROR(_xlfn.XLOOKUP(A13,Table2[SKU_Code],Table2[Received_Qty]),"Missing") -> 139 | D13: =IFERROR(SUMIF(Table4[SKU_Code], A13, Table4[Qty]), "Missing") -> 42 | E13: =IFERROR(D13/C13,"Missing") -> 0.30215827 | F13: =IFERROR(_xlfn.XLOOKUP(A13, Table1[SKU_Code], Table1[Cost_IRR]), "Missing") -> 140000 | G13: =IFERROR(_xlfn.XLOOKUP(A13,Table1[SKU_Code],Table1[RRP_IRR]),"Missing") -> 320000 | H13: =IFERROR((G13-F13)/G13, "Missing") -> 0.5625 | I13: =SUMIF(Table4[SKU_Code],'Financial Analysis'!A13,Table4[Revenue]) -> 13184000 | J13: =_xlfn.RANK.EQ(I13,$I$2:$I$41,0) -> 21 | K13: =SUMIF($J$2:$J$41,"<="&J13,$I$2:$I$41)/SUM($I$2:$I$41) -> 0.68752134 | L13: =IF(K13<=0.7,"A",IF(K13<=0.9,"B","C")) -> A | M13: =I13-(D13*F13) -> 7304000 | N13: =C13*F13 -> 19460000 | O13: =IFERROR(ROUND(M13/N13,2),"Missing") -> 0.38 | P13: =IF(O13>=2,"A",IF(O13>=1,"B","C")) -> C
A14: PRD-013 | B14: Brown Turtleneck Knit | C14: =IFERROR(_xlfn.XLOOKUP(A14,Table2[SKU_Code],Table2[Received_Qty]),"Missing") -> 46 | D14: =IFERROR(SUMIF(Table4[SKU_Code], A14, Table4[Qty]), "Missing") -> 61 | E14: =IFERROR(D14/C14,"Missing") -> 1.326087 | F14: =IFERROR(_xlfn.XLOOKUP(A14, Table1[SKU_Code], Table1[Cost_IRR]), "Missing") -> 120000 | G14: =IFERROR(_xlfn.XLOOKUP(A14,Table1[SKU_Code],Table1[RRP_IRR]),"Missing") -> 280000 | H14: =IFERROR((G14-F14)/G14, "Missing") -> 0.57142857 | I14: =SUMIF(Table4[SKU_Code],'Financial Analysis'!A14,Table4[Revenue]) -> 16478000 | J14: =_xlfn.RANK.EQ(I14,$I$2:$I$41,0) -> 13 | K14: =SUMIF($J$2:$J$41,"<="&J14,$I$2:$I$41)/SUM($I$2:$I$41) -> 0.49831417 | L14: =IF(K14<=0.7,"A",IF(K14<=0.9,"B","C")) -> A | M14: =I14-(D14*F14) -> 9158000 | N14: =C14*F14 -> 5520000 | O14: =IFERROR(ROUND(M14/N14,2),"Missing") -> 1.66 | P14: =IF(O14>=2,"A",IF(O14>=1,"B","C")) -> B
A15: PRD-014 | B15: Cable Knit Vest White | C15: =IFERROR(_xlfn.XLOOKUP(A15,Table2[SKU_Code],Table2[Received_Qty]),"Missing") -> 62 | D15: =IFERROR(SUMIF(Table4[SKU_Code], A15, Table4[Qty]), "Missing") -> 55 | E15: =IFERROR(D15/C15,"Missing") -> 0.88709677 | F15: =IFERROR(_xlfn.XLOOKUP(A15, Table1[SKU_Code], Table1[Cost_IRR]), "Missing") -> 110000 | G15: =IFERROR(_xlfn.XLOOKUP(A15,Table1[SKU_Code],Table1[RRP_IRR]),"Missing") -> 260000 | H15: =IFERROR((G15-F15)/G15, "Missing") -> 0.57692308 | I15: =SUMIF(Table4[SKU_Code],'Financial Analysis'!A15,Table4[Revenue]) -> 13897000 | J15: =_xlfn.RANK.EQ(I15,$I$2:$I$41,0) -> 18 | K15: =SUMIF($J$2:$J$41,"<="&J15,$I$2:$I$41)/SUM($I$2:$I$41) -> 0.61980148 | L15: =IF(K15<=0.7,"A",IF(K15<=0.9,"B","C")) -> A | M15: =I15-(D15*F15) -> 7847000 | N15: =C15*F15 -> 6820000 | O15: =IFERROR(ROUND(M15/N15,2),"Missing") -> 1.15 | P15: =IF(O15>=2,"A",IF(O15>=1,"B","C")) -> B
A16: PRD-015 | B16: Cable Knit Vest White | C16: =IFERROR(_xlfn.XLOOKUP(A16,Table2[SKU_Code],Table2[Received_Qty]),"Missing") -> 37 | D16: =IFERROR(SUMIF(Table4[SKU_Code], A16, Table4[Qty]), "Missing") -> 43 | E16: =IFERROR(D16/C16,"Missing") -> 1.1621622 | F16: =IFERROR(_xlfn.XLOOKUP(A16, Table1[SKU_Code], Table1[Cost_IRR]), "Missing") -> 110000 | G16: =IFERROR(_xlfn.XLOOKUP(A16,Table1[SKU_Code],Table1[RRP_IRR]),"Missing") -> 260000 | H16: =IFERROR((G16-F16)/G16, "Missing") -> 0.57692308 | I16: =SUMIF(Table4[SKU_Code],'Financial Analysis'!A16,Table4[Revenue]) -> 11115000 | J16: =_xlfn.RANK.EQ(I16,$I$2:$I$41,0) -> 27 | K16: =SUMIF($J$2:$J$41,"<="&J16,$I$2:$I$41)/SUM($I$2:$I$41) -> 0.80900275 | L16: =IF(K16<=0.7,"A",IF(K16<=0.9,"B","C")) -> B | M16: =I16-(D16*F16) -> 6385000 | N16: =C16*F16 -> 4070000 | O16: =IFERROR(ROUND(M16/N16,2),"Missing") -> 1.57 | P16: =IF(O16>=2,"A",IF(O16>=1,"B","C")) -> B
A17: PRD-016 | B17: Grey Hoodie | C17: =IFERROR(_xlfn.XLOOKUP(A17,Table2[SKU_Code],Table2[Received_Qty]),"Missing") -> 38 | D17: =IFERROR(SUMIF(Table4[SKU_Code], A17, Table4[Qty]), "Missing") -> 39 | E17: =IFERROR(D17/C17,"Missing") -> 1.0263158 | F17: =IFERROR(_xlfn.XLOOKUP(A17, Table1[SKU_Code], Table1[Cost_IRR]), "Missing") -> 105000 | G17: =IFERROR(_xlfn.XLOOKUP(A17,Table1[SKU_Code],Table1[RRP_IRR]),"Missing") -> 235000 | H17: =IFERROR((G17-F17)/G17, "Missing") -> 0.55319149 | I17: =SUMIF(Table4[SKU_Code],'Financial Analysis'!A17,Table4[Revenue]) -> 8988750 | J17: =_xlfn.RANK.EQ(I17,$I$2:$I$41,0) -> 33 | K17: =SUMIF($J$2:$J$41,"<="&J17,$I$2:$I$41)/SUM($I$2:$I$41) -> 0.91069231 | L17: =IF(K17<=0.7,"A",IF(K17<=0.9,"B","C")) -> C | M17: =I17-(D17*F17) -> 4893750 | N17: =C17*F17 -> 3990000 | O17: =IFERROR(ROUND(M17/N17,2),"Missing") -> 1.23 | P17: =IF(O17>=2,"A",IF(O17>=1,"B","C")) -> B
A18: PRD-017 | B18: Grey Hoodie | C18: =IFERROR(_xlfn.XLOOKUP(A18,Table2[SKU_Code],Table2[Received_Qty]),"Missing") -> 139 | D18: =IFERROR(SUMIF(Table4[SKU_Code], A18, Table4[Qty]), "Missing") -> 46 | E18: =IFERROR(D18/C18,"Missing") -> 0.33093525 | F18: =IFERROR(_xlfn.XLOOKUP(A18, Table1[SKU_Code], Table1[Cost_IRR]), "Missing") -> 105000 | G18: =IFERROR(_xlfn.XLOOKUP(A18,Table1[SKU_Code],Table1[RRP_IRR]),"Missing") -> 235000 | H18: =IFERROR((G18-F18)/G18, "Missing") -> 0.55319149 | I18: =SUMIF(Table4[SKU_Code],'Financial Analysis'!A18,Table4[Revenue]) -> 10387000 | J18: =_xlfn.RANK.EQ(I18,$I$2:$I$41,0) -> 29 | K18: =SUMIF($J$2:$J$41,"<="&J18,$I$2:$I$41)/SUM($I$2:$I$41) -> 0.84502681 | L18: =IF(K18<=0.7,"A",IF(K18<=0.9,"B","C")) -> B | M18: =I18-(D18*F18) -> 5557000 | N18: =C18*F18 -> 14595000 | O18: =IFERROR(ROUND(M18/N18,2),"Missing") -> 0.38 | P18: =IF(O18>=2,"A",IF(O18>=1,"B","C")) -> C
A19: PRD-018 | B19: White Linen Shirt | C19: =IFERROR(_xlfn.XLOOKUP(A19,Table2[SKU_Code],Table2[Received_Qty]),"Missing") -> 129 | D19: =IFERROR(SUMIF(Table4[SKU_Code], A19, Table4[Qty]), "Missing") -> 46 | E19: =IFERROR(D19/C19,"Missing") -> 0.35658915 | F19: =IFERROR(_xlfn.XLOOKUP(A19, Table1[SKU_Code], Table1[Cost_IRR]), "Missing") -> 85000 | G19: =IFERROR(_xlfn.XLOOKUP(A19,Table1[SKU_Code],Table1[RRP_IRR]),"Missing") -> 195000 | H19: =IFERROR((G19-F19)/G19, "Missing") -> 0.56410256 | I19: =SUMIF(Table4[SKU_Code],'Financial Analysis'!A19,Table4[Revenue]) -> 8443500 | J19: =_xlfn.RANK.EQ(I19,$I$2:$I$41,0) -> 34 | K19: =SUMIF($J$2:$J$41,"<="&J19,$I$2:$I$41)/SUM($I$2:$I$41) -> 0.9249138 | L19: =IF(K19<=0.7,"A",IF(K19<=0.9,"B","C")) -> C | M19: =I19-(D19*F19) -> 4533500 | N19: =C19*F19 -> 10965000 | O19: =IFERROR(ROUND(M19/N19,2),"Missing") -> 0.41 | P19: =IF(O19>=2,"A",IF(O19>=1,"B","C")) -> C
A20: PRD-019 | B20: White Linen Shirt | C20: =IFERROR(_xlfn.XLOOKUP(A20,Table2[SKU_Code],Table2[Received_Qty]),"Missing") -> 66 | D20: =IFERROR(SUMIF(Table4[SKU_Code], A20, Table4[Qty]), "Missing") -> 54 | E20: =IFERROR(D20/C20,"Missing") -> 0.81818182 | F20: =IFERROR(_xlfn.XLOOKUP(A20, Table1[SKU_Code], Table1[Cost_IRR]), "Missing") -> 85000 | G20: =IFERROR(_xlfn.XLOOKUP(A20,Table1[SKU_Code],Table1[RRP_IRR]),"Missing") -> 195000 | H20: =IFERROR((G20-F20)/G20, "Missing") -> 0.56410256 | I20: =SUMIF(Table4[SKU_Code],'Financial Analysis'!A20,Table4[Revenue]) -> 10354500 | J20: =_xlfn.RANK.EQ(I20,$I$2:$I$41,0) -> 30 | K20: =SUMIF($J$2:$J$41,"<="&J20,$I$2:$I$41)/SUM($I$2:$I$41) -> 0.86246701 | L20: =IF(K20<=0.7,"A",IF(K20<=0.9,"B","C")) -> B | M20: =I20-(D20*F20) -> 5764500 | N20: =C20*F20 -> 5610000 | O20: =IFERROR(ROUND(M20/N20,2),"Missing") -> 1.03 | P20: =IF(O20>=2,"A",IF(O20>=1,"B","C")) -> B
... A41: PRD-040 | B41: Navy Wide Leg Pants | C41: =IFERROR(_xlfn.XLOOKUP(A41,Table2[SKU_Code],Table2[Received_Qty]),"Missing") -> 37 | D41: =IFERROR(SUMIF(Table4[SKU_Code], A41, Table4[Qty]), "Missing") -> 47 | E41: =IFERROR(D41/C41,"Missing") -> 1.2702703 | F41: =IFERROR(_xlfn.XLOOKUP(A41, Table1[SKU_Code], Table1[Cost_IRR]), "Missing") -> 80000 | G41: =IFERROR(_xlfn.XLOOKUP(A41,Table1[SKU_Code],Table1[RRP_IRR]),"Missing") -> 182000 | H41: =IFERROR((G41-F41)/G41, "Missing") -> 0.56043956 | I41: =SUMIF(Table4[SKU_Code],'Financial Analysis'!A41,Table4[Revenue]) -> 8235500 | J41: =_xlfn.RANK.EQ(I41,$I$2:$I$41,0) -> 37 | K41: =SUMIF($J$2:$J$41,"<="&J41,$I$2:$I$41)/SUM($I$2:$I$41) -> 0.96688432 | L41: =IF(K41<=0.7,"A",IF(K41<=0.9,"B","C")) -> C | M41: =I41-(D41*F41) -> 4475500 | N41: =C41*F41 -> 2960000 | O41: =IFERROR(ROUND(M41/N41,2),"Missing") -> 1.51 | P41: =IF(O41>=2,"A",IF(O41>=1,"B","C")) -> B

Sheet Advanced Analysis
A1: Chapter 7 — Advanced Analysis
A2: 7.1 Sensitivity Analysis — Demand Spike Scenario
A4: Assumptions
A5: Z-Score (Service Level) | B5: 1.65
A6: Lead Time (Days) | B6: 14
A7: Spike Levels | B7: 0.25 | C7: 0.5 | D7: 0.75
F8: 25% Spike Scenario | J8: 50% Spike Scenario | N8: 75% Spike Scenario
A9: SKU_Code | B9: Avg_Daily_Demand | C9: Std_Dev | D9: Base_Safety_Stock | E9: Units_On_Hand | F9: Safety_Stock_25% | G9: ROP_25% | H9: Days_of_Supply_25% | I9: Stockout_25% | J9: Safety_Stock_50% | K9: ROP_50% | L9: Days_of_Supply_50% | M9: Stockout_50% | N9: Safety_Stock_75% | O9: ROP_75% | P9: Days_of_Supply_75% | Q9: Stockout_75%
A10: ='Inventory Analysis'!A2 -> PRD-001 | B10: ='Inventory Analysis'!F2 -> 0.12 | C10: ='Inventory Analysis'!E2 -> 2.489648 | D10: =ROUND($B$5*C10*SQRT($B$6/30),0) -> 3 | E10: ='Inventory Analysis'!J2 -> 3 | F10: =ROUND($B$5*(C10*(1+B$7))*SQRT($B$6/30),0) -> 4 | G10: =ROUND((B10*(1+$B$7))*$B$6+F10,0) -> 6 | H10: =IF(E10="Missing",0,ROUND(E10/(B10*(1+$B$7)),0)) -> 20 | I10: =IF(E10="Missing","Missing",IF(E10<G10,"Danger",IF(E10<G10*1.2,"Watch","Stable"))) -> Danger | J10: =ROUND($B$5*(C10*(1+C$7))*SQRT($B$6/30),0) -> 4 | K10: =ROUND((B10*(1+$C$7))*$B$6+J10,0) -> 7 | L10: =IF(E10="Missing",0,ROUND(E10/(B10*(1+C$7)),0)) -> 17 | M10: =IF(E10="Missing","Missing",IF(E10<K10,"Danger",IF(E10<K10*1.2,"Watch","Stable"))) -> Danger | N10: =ROUND($B$5*(C10*(1+$D$7))*SQRT($B$6/30),0) -> 5 | O10: =ROUND((B10*(1+D$7))*$B$6+N10,0) -> 8 | P10: =IF(E10="Missing",0,ROUND(E10/(B10*(1+D$7)),0)) -> 14 | Q10: =IF(E10="Missing","Missing",IF(E10<O10,"Danger",IF(E10<O10*1.2,"Watch","Stable"))) -> Danger
A11: ='Inventory Analysis'!A3 -> PRD-002 | B11: ='Inventory Analysis'!F3 -> 0.19 | C11: ='Inventory Analysis'!E3 -> 4.1857895 | D11: =ROUND($B$5*C11*SQRT($B$6/30),0) -> 5 | E11: ='Inventory Analysis'!J3 -> 23 | F11: =ROUND($B$5*(C11*(1+B$7))*SQRT($B$6/30),0) -> 6 | G11: =ROUND((B11*(1+$B$7))*$B$6+F11,0) -> 9 | H11: =IF(E11="Missing",0,ROUND(E11/(B11*(1+$B$7)),0)) -> 97 | I11: =IF(E11="Missing","Missing",IF(E11<G11,"Danger",IF(E11<G11*1.2,"Watch","Stable"))) -> Stable | J11: =ROUND($B$5*(C11*(1+C$7))*SQRT($B$6/30),0) -> 7 | K11: =ROUND((B11*(1+$C$7))*$B$6+J11,0) -> 11 | L11: =IF(E11="Missing",0,ROUND(E11/(B11*(1+C$7)),0)) -> 81 | M11: =IF(E11="Missing","Missing",IF(E11<K11,"Danger",IF(E11<K11*1.2,"Watch","Stable"))) -> Stable | N11: =ROUND($B$5*(C11*(1+$D$7))*SQRT($B$6/30),0) -> 8 | O11: =ROUND((B11*(1+D$7))*$B$6+N11,0) -> 13 | P11: =IF(E11="Missing",0,ROUND(E11/(B11*(1+D$7)),0)) -> 69 | Q11: =IF(E11="Missing","Missing",IF(E11<O11,"Danger",IF(E11<O11*1.2,"Watch","Stable"))) -> Stable
A12: ='Inventory Analysis'!A4 -> PRD-003 | B12: ='Inventory Analysis'!F4 -> 0.19 | C12: ='Inventory Analysis'!E4 -> 3.7239453 | D12: =ROUND($B$5*C12*SQRT($B$6/30),0) -> 4 | E12: ='Inventory Analysis'!J4 -> 4 | F12: =ROUND($B$5*(C12*(1+B$7))*SQRT($B$6/30),0) -> 5 | G12: =ROUND((B12*(1+$B$7))*$B$6+F12,0) -> 8 | H12: =IF(E12="Missing",0,ROUND(E12/(B12*(1+$B$7)),0)) -> 17 | I12: =IF(E12="Missing","Missing",IF(E12<G12,"Danger",IF(E12<G12*1.2,"Watch","Stable"))) -> Danger | J12: =ROUND($B$5*(C12*(1+C$7))*SQRT($B$6/30),0) -> 6 | K12: =ROUND((B12*(1+$C$7))*$B$6+J12,0) -> 10 | L12: =IF(E12="Missing",0,ROUND(E12/(B12*(1+C$7)),0)) -> 14 | M12: =IF(E12="Missing","Missing",IF(E12<K12,"Danger",IF(E12<K12*1.2,"Watch","Stable"))) -> Danger | N12: =ROUND($B$5*(C12*(1+$D$7))*SQRT($B$6/30),0) -> 7 | O12: =ROUND((B12*(1+D$7))*$B$6+N12,0) -> 12 | P12: =IF(E12="Missing",0,ROUND(E12/(B12*(1+D$7)),0)) -> 12 | Q12: =IF(E12="Missing","Missing",IF(E12<O12,"Danger",IF(E12<O12*1.2,"Watch","Stable"))) -> Danger
A13: ='Inventory Analysis'!A5 -> PRD-004 | B13: ='Inventory Analysis'!F5 -> 0.19 | C13: ='Inventory Analysis'!E5 -> 3.2218264 | D13: =ROUND($B$5*C13*SQRT($B$6/30),0) -> 4 | E13: ='Inventory Analysis'!J5 -> 13 | F13: =ROUND($B$5*(C13*(1+B$7))*SQRT($B$6/30),0) -> 5 | G13: =ROUND((B13*(1+$B$7))*$B$6+F13,0) -> 8 | H13: =IF(E13="Missing",0,ROUND(E13/(B13*(1+$B$7)),0)) -> 55 | I13: =IF(E13="Missing","Missing",IF(E13<G13,"Danger",IF(E13<G13*1.2,"Watch","Stable"))) -> Stable | J13: =ROUND($B$5*(C13*(1+C$7))*SQRT($B$6/30),0) -> 5 | K13: =ROUND((B13*(1+$C$7))*$B$6+J13,0) -> 9 | L13: =IF(E13="Missing",0,ROUND(E13/(B13*(1+C$7)),0)) -> 46 | M13: =IF(E13="Missing","Missing",IF(E13<K13,"Danger",IF(E13<K13*1.2,"Watch","Stable"))) -> Stable | N13: =ROUND($B$5*(C13*(1+D$7))*SQRT($B$6/30),0) -> 6 | O13: =ROUND((B13*(1+D$7))*$B$6+N13,0) -> 11 | P13: =IF(E13="Missing",0,ROUND(E13/(B13*(1+D$7)),0)) -> 39 | Q13: =IF(E13="Missing","Missing",IF(E13<O13,"Danger",IF(E13<O13*1.2,"Watch","Stable"))) -> Watch
A14: ='Inventory Analysis'!A6 -> PRD-005 | B14: ='Inventory Analysis'!F6 -> 0.23 | C14: ='Inventory Analysis'!E6 -> 4.1665333 | D14: =ROUND($B$5*C14*SQRT($B$6/30),0) -> 5 | E14: ='Inventory Analysis'!J6 -> 22 | F14: =ROUND($B$5*(C14*(1+B$7))*SQRT($B$6/30),0) -> 6 | G14: =ROUND((B14*(1+$B$7))*$B$6+F14,0) -> 10 | H14: =IF(E14="Missing",0,ROUND(E14/(B14*(1+$B$7)),0)) -> 77 | I14: =IF(E14="Missing","Missing",IF(E14<G14,"Danger",IF(E14<G14*1.2,"Watch","Stable"))) -> Stable | J14: =ROUND($B$5*(C14*(1+C$7))*SQRT($B$6/30),0) -> 7 | K14: =ROUND((B14*(1+$C$7))*$B$6+J14,0) -> 12 | L14: =IF(E14="Missing",0,ROUND(E14/(B14*(1+C$7)),0)) -> 64 | M14: =IF(E14="Missing","Missing",IF(E14<K14,"Danger",IF(E14<K14*1.2,"Watch","Stable"))) -> Stable | N14: =ROUND($B$5*(C14*(1+D$7))*SQRT($B$6/30),0) -> 8 | O14: =ROUND((B14*(1+D$7))*$B$6+N14,0) -> 14 | P14: =IF(E14="Missing",0,ROUND(E14/(B14*(1+D$7)),0)) -> 55 | Q14: =IF(E14="Missing","Missing",IF(E14<O14,"Danger",IF(E14<O14*1.2,"Watch","Stable"))) -> Stable
A15: ='Inventory Analysis'!A7 -> PRD-006 | B15: ='Inventory Analysis'!F7 -> 0.16 | C15: ='Inventory Analysis'!E7 -> 3.8613109 | D15: =ROUND($B$5*C15*SQRT($B$6/30),0) -> 4 | E15: ='Inventory Analysis'!J7 -> 40 | F15: =ROUND($B$5*(C15*(1+B$7))*SQRT($B$6/30),0) -> 5 | G15: =ROUND((B15*(1+$B$7))*$B$6+F15,0) -> 8 | H15: =IF(E15="Missing",0,ROUND(E15/(B15*(1+$B$7)),0)) -> 200 | I15: =IF(E15="Missing","Missing",IF(E15<G15,"Danger",IF(E15<G15*1.2,"Watch","Stable"))) -> Stable | J15: =ROUND($B$5*(C15*(1+C$7))*SQRT($B$6/30),0) -> 7 | K15: =ROUND((B15*(1+$C$7))*$B$6+J15,0) -> 10 | L15: =IF(E15="Missing",0,ROUND(E15/(B15*(1+C$7)),0)) -> 167 | M15: =IF(E15="Missing","Missing",IF(E15<K15,"Danger",IF(E15<K15*1.2,"Watch","Stable"))) -> Stable | N15: =ROUND($B$5*(C15*(1+D$7))*SQRT($B$6/30),0) -> 8 | O15: =ROUND((B15*(1+D$7))*$B$6+N15,0) -> 12 | P15: =IF(E15="Missing",0,ROUND(E15/(B15*(1+D$7)),0)) -> 143 | Q15: =IF(E15="Missing","Missing",IF(E15<O15,"Danger",IF(E15<O15*1.2,"Watch","Stable"))) -> Stable
A16: ='Inventory Analysis'!A8 -> PRD-007 | B16: ='Inventory Analysis'!F8 -> 0.18 | C16: ='Inventory Analysis'!E8 -> 3.1069105 | D16: =ROUND($B$5*C16*SQRT($B$6/30),0) -> 4 | E16: ='Inventory Analysis'!J8 -> 9 | F16: =ROUND($B$5*(C16*(1+B$7))*SQRT($B$6/30),0) -> 4 | G16: =ROUND((B16*(1+$B$7))*$B$6+F16,0) -> 7 | H16: =IF(E16="Missing",0,ROUND(E16/(B16*(1+$B$7)),0)) -> 40 | I16: =IF(E16="Missing","Missing",IF(E16<G16,"Danger",IF(E16<G16*1.2,"Watch","Stable"))) -> Stable | J16: =ROUND($B$5*(C16*(1+C$7))*SQRT($B$6/30),0) -> 5 | K16: =ROUND((B16*(1+$C$7))*$B$6+J16,0) -> 9 | L16: =IF(E16="Missing",0,ROUND(E16/(B16*(1+C$7)),0)) -> 33 | M16: =IF(E16="Missing","Missing",IF(E16<K16,"Danger",IF(E16<K16*1.2,"Watch","Stable"))) -> Watch | N16: =ROUND($B$5*(C16*(1+D$7))*SQRT($B$6/30),0) -> 6 | O16: =ROUND((B16*(1+D$7))*$B$6+N16,0) -> 10 | P16: =IF(E16="Missing",0,ROUND(E16/(B16*(1+D$7)),0)) -> 29 | Q16: =IF(E16="Missing","Missing",IF(E16<O16,"Danger",IF(E16<O16*1.2,"Watch","Stable"))) -> Danger
A17: ='Inventory Analysis'!A9 -> PRD-008 | B17: ='Inventory Analysis'!F9 -> 0.22 | C17: ='Inventory Analysis'!E9 -> 4.8820806 | D17: =ROUND($B$5*C17*SQRT($B$6/30),0) -> 6 | E17: ='Inventory Analysis'!J9 -> Missing | F17: =ROUND($B$5*(C17*(1+B$7))*SQRT($B$6/30),0) -> 7 | G17: =ROUND((B17*(1+$B$7))*$B$6+F17,0) -> 11 | H17: =IF(E17="Missing",0,ROUND(E17/(B17*(1+$B$7)),0)) -> 0 | I17: =IF(E17="Missing","Missing",IF(E17<G17,"Danger",IF(E17<G17*1.2,"Watch","Stable"))) -> Missing | J17: =ROUND($B$5*(C17*(1+C$7))*SQRT($B$6/30),0) -> 8 | K17: =ROUND((B17*(1+$C$7))*$B$6+J17,0) -> 13 | L17: =IF(E17="Missing",0,ROUND(E17/(B17*(1+C$7)),0)) -> 0 | M17: =IF(E17="Missing","Missing",IF(E17<K17,"Danger",IF(E17<K17*1.2,"Watch","Stable"))) -> Missing | N17: =ROUND($B$5*(C17*(1+D$7))*SQRT($B$6/30),0) -> 10 | O17: =ROUND((B17*(1+D$7))*$B$6+N17,0) -> 15 | P17: =IF(E17="Missing",0,ROUND(E17/(B17*(1+D$7)),0)) -> 0 | Q17: =IF(E17="Missing","Missing",IF(E17<O17,"Danger",IF(E17<O17*1.2,"Watch","Stable"))) -> Missing
A18: ='Inventory Analysis'!A10 -> PRD-009 | B18: ='Inventory Analysis'!F10 -> 0.22 | C18: ='Inventory Analysis'!E10 -> 3.4208887 | D18: =ROUND($B$5*C18*SQRT($B$6/30),0) -> 4 | E18: ='Inventory Analysis'!J10 -> 2 | F18: =ROUND($B$5*(C18*(1+B$7))*SQRT($B$6/30),0) -> 5 | G18: =ROUND((B18*(1+$B$7))*$B$6+F18,0) -> 9 | H18: =IF(E18="Missing",0,ROUND(E18/(B18*(1+$B$7)),0)) -> 7 | I18: =IF(E18="Missing","Missing",IF(E18<G18,"Danger",IF(E18<G18*1.2,"Watch","Stable"))) -> Danger | J18: =ROUND($B$5*(C18*(1+C$7))*SQRT($B$6/30),0) -> 6 | K18: =ROUND((B18*(1+$C$7))*$B$6+J18,0) -> 11 | L18: =IF(E18="Missing",0,ROUND(E18/(B18*(1+C$7)),0)) -> 6 | M18: =IF(E18="Missing","Missing",IF(E18<K18,"Danger",IF(E18<K18*1.2,"Watch","Stable"))) -> Danger | N18: =ROUND($B$5*(C18*(1+D$7))*SQRT($B$6/30),0) -> 7 | O18: =ROUND((B18*(1+D$7))*$B$6+N18,0) -> 12 | P18: =IF(E18="Missing",0,ROUND(E18/(B18*(1+D$7)),0)) -> 5 | Q18: =IF(E18="Missing","Missing",IF(E18<O18,"Danger",IF(E18<O18*1.2,"Watch","Stable"))) -> Danger
A19: ='Inventory Analysis'!A11 -> PRD-010 | B19: ='Inventory Analysis'!F11 -> 0.12 | C19: ='Inventory Analysis'!E11 -> 2.3845231 | D19: =ROUND($B$5*C19*SQRT($B$6/30),0) -> 3 | E19: ='Inventory Analysis'!J11 -> 10 | F19: =ROUND($B$5*(C19*(1+B$7))*SQRT($B$6/30),0) -> 3 | G19: =ROUND((B19*(1+$B$7))*$B$6+F19,0) -> 5 | H19: =IF(E19="Missing",0,ROUND(E19/(B19*(1+$B$7)),0)) -> 67 | I19: =IF(E19="Missing","Missing",IF(E19<G19,"Danger",IF(E19<G19*1.2,"Watch","Stable"))) -> Stable | J19: =ROUND($B$5*(C19*(1+C$7))*SQRT($B$6/30),0) -> 4 | K19: =ROUND((B19*(1+$C$7))*$B$6+J19,0) -> 7 | L19: =IF(E19="Missing",0,ROUND(E19/(B19*(1+C$7)),0)) -> 56 | M19: =IF(E19="Missing","Missing",IF(E19<K19,"Danger",IF(E19<K19*1.2,"Watch","Stable"))) -> Stable | N19: =ROUND($B$5*(C19*(1+D$7))*SQRT($B$6/30),0) -> 5 | O19: =ROUND((B19*(1+D$7))*$B$6+N19,0) -> 8 | P19: =IF(E19="Missing",0,ROUND(E19/(B19*(1+D$7)),0)) -> 48 | Q19: =IF(E19="Missing","Missing",IF(E19<O19,"Danger",IF(E19<O19*1.2,"Watch","Stable"))) -> Stable
A20: ='Inventory Analysis'!A12 -> PRD-011 | B20: ='Inventory Analysis'!F12 -> 0.13 | C20: ='Inventory Analysis'!E12 -> 3.4292856 | D20: =ROUND($B$5*C20*SQRT($B$6/30),0) -> 4 | E20: ='Inventory Analysis'!J12 -> 35 | F20: =ROUND($B$5*(C20*(1+B$7))*SQRT($B$6/30),0) -> 5 | G20: =ROUND((B20*(1+$B$7))*$B$6+F20,0) -> 7 | H20: =IF(E20="Missing",0,ROUND(E20/(B20*(1+$B$7)),0)) -> 215 | I20: =IF(E20="Missing","Missing",IF(E20<G20,"Danger",IF(E20<G20*1.2,"Watch","Stable"))) -> Stable | J20: =ROUND($B$5*(C20*(1+C$7))*SQRT($B$6/30),0) -> 6 | K20: =ROUND((B20*(1+$C$7))*$B$6+J20,0) -> 9 | L20: =IF(E20="Missing",0,ROUND(E20/(B20*(1+C$7)),0)) -> 179 | M20: =IF(E20="Missing","Missing",IF(E20<K20,"Danger",IF(E20<K20*1.2,"Watch","Stable"))) -> Stable | N20: =ROUND($B$5*(C20*(1+D$7))*SQRT($B$6/30),0) -> 7 | O20: =ROUND((B20*(1+D$7))*$B$6+N20,0) -> 10 | P20: =IF(E20="Missing",0,ROUND(E20/(B20*(1+D$7)),0)) -> 154 | Q20: =IF(E20="Missing","Missing",IF(E20<O20,"Danger",IF(E20<O20*1.2,"Watch","Stable"))) -> Stable
A21: ='Inventory Analysis'!A13 -> PRD-012 | B21: ='Inventory Analysis'!F13 -> 0.14 | C21: ='Inventory Analysis'!E13 -> 3.4583233 | D21: =ROUND($B$5*C21*SQRT($B$6/30),0) -> 4 | E21: ='Inventory Analysis'!J13 -> 16 | F21: =ROUND($B$5*(C21*(1+B$7))*SQRT($B$6/30),0) -> 5 | G21: =ROUND((B21*(1+$B$7))*$B$6+F21,0) -> 7 | H21: =IF(E21="Missing",0,ROUND(E21/(B21*(1+$B$7)),0)) -> 91 | I21: =IF(E21="Missing","Missing",IF(E21<G21,"Danger",IF(E21<G21*1.2,"Watch","Stable"))) -> Stable | J21: =ROUND($B$5*(C21*(1+C$7))*SQRT($B$6/30),0) -> 6 | K21: =ROUND((B21*(1+$C$7))*$B$6+J21,0) -> 9 | L21: =IF(E21="Missing",0,ROUND(E21/(B21*(1+C$7)),0)) -> 76 | M21: =IF(E21="Missing","Missing",IF(E21<K21,"Danger",IF(E21<K21*1.2,"Watch","Stable"))) -> Stable | N21: =ROUND($B$5*(C21*(1+D$7))*SQRT($B$6/30),0) -> 7 | O21: =ROUND((B21*(1+D$7))*$B$6+N21,0) -> 10 | P21: =IF(E21="Missing",0,ROUND(E21/(B21*(1+D$7)),0)) -> 65 | Q21: =IF(E21="Missing","Missing",IF(E21<O21,"Danger",IF(E21<O21*1.2,"Watch","Stable"))) -> Stable
A22: ='Inventory Analysis'!A14 -> PRD-013 | B22: ='Inventory Analysis'!F14 -> 0.17 | C22: ='Inventory Analysis'!E14 -> 3.0675271 | D22: =ROUND($B$5*C22*SQRT($B$6/30),0) -> 3 | E22: ='Inventory Analysis'!J14 -> 10 | F22: =ROUND($B$5*(C22*(1+B$7))*SQRT($B$6/30),0) -> 4 | G22: =ROUND((B22*(1+$B$7))*$B$6+F22,0) -> 7 | H22: =IF(E22="Missing",0,ROUND(E22/(B22*(1+$B$7)),0)) -> 47 | I22: =IF(E22="Missing","Missing",IF(E22<G22,"Danger",IF(E22<G22*1.2,"Watch","Stable"))) -> Stable | J22: =ROUND($B$5*(C22*(1+C$7))*SQRT($B$6/30),0) -> 5 | K22: =ROUND((B22*(1+$C$7))*$B$6+J22,0) -> 9 | L22: =IF(E22="Missing",0,ROUND(E22/(B22*(1+C$7)),0)) -> 39 | M22: =IF(E22="Missing","Missing",IF(E22<K22,"Danger",IF(E22<K22*1.2,"Watch","Stable"))) -> Watch | N22: =ROUND($B$5*(C22*(1+D$7))*SQRT($B$6/30),0) -> 6 | O22: =ROUND((B22*(1+D$7))*$B$6+N22,0) -> 10 | P22: =IF(E22="Missing",0,ROUND(E22/(B22*(1+D$7)),0)) -> 34 | Q22: =IF(E22="Missing","Missing",IF(E22<O22,"Danger",IF(E22<O22*1.2,"Watch","Stable"))) -> Watch
A23: ='Inventory Analysis'!A15 -> PRD-014 | B23: ='Inventory Analysis'!F15 -> 0.18 | C23: ='Inventory Analysis'!E15 -> 4.0062451 | D23: =ROUND($B$5*C23*SQRT($B$6/30),0) -> 5 | E23: ='Inventory Analysis'!J15 -> 40 | F23: =ROUND($B$5*(C23*(1+B$7))*SQRT($B$6/30),0) -> 6 | G23: =ROUND((B23*(1+$B$7))*$B$6+F23,0) -> 9 | H23: =IF(E23="Missing",0,ROUND(E23/(B23*(1+$B$7)),0)) -> 178 | I23: =IF(E23="Missing","Missing",IF(E23<G23,"Danger",IF(E23<G23*1.2,"Watch","Stable"))) -> Stable | J23: =ROUND($B$5*(C23*(1+C$7))*SQRT($B$6/30),0) -> 7 | K23: =ROUND((B23*(1+$C$7))*$B$6+J23,0) -> 11 | L23: =IF(E23="Missing",0,ROUND(E23/(B23*(1+C$7)),0)) -> 148 | M23: =IF(E23="Missing","Missing",IF(E23<K23,"Danger",IF(E23<K23*1.2,"Watch","Stable"))) -> Stable | N23: =ROUND($B$5*(C23*(1+D$7))*SQRT($B$6/30),0) -> 8 | O23: =ROUND((B23*(1+D$7))*$B$6+N23,0) -> 12 | P23: =IF(E23="Missing",0,ROUND(E23/(B23*(1+D$7)),0)) -> 127 | Q23: =IF(E23="Missing","Missing",IF(E23<O23,"Danger",IF(E23<O23*1.2,"Watch","Stable"))) -> Stable
A24: ='Inventory Analysis'!A16 -> PRD-015 | B24: ='Inventory Analysis'!F16 -> 0.14 | C24: ='Inventory Analysis'!E16 -> 2.9681644 | D24: =ROUND($B$5*C24*SQRT($B$6/30),0) -> 3 | E24: ='Inventory Analysis'!J16 -> 3 | F24: =ROUND($B$5*(C24*(1+B$7))*SQRT($B$6/30),0) -> 4 | G24: =ROUND((B24*(1+$B$7))*$B$6+F24,0) -> 6 | H24: =IF(E24="Missing",0,ROUND(E24/(B24*(1+$B$7)),0)) -> 17 | I24: =IF(E24="Missing","Missing",IF(E24<G24,"Danger",IF(E24<G24*1.2,"Watch","Stable"))) -> Danger | J24: =ROUND($B$5*(C24*(1+C$7))*SQRT($B$6/30),0) -> 5 | K24: =ROUND((B24*(1+$C$7))*$B$6+J24,0) -> 8 | L24: =IF(E24="Missing",0,ROUND(E24/(B24*(1+C$7)),0)) -> 14 | M24: =IF(E24="Missing","Missing",IF(E24<K24,"Danger",IF(E24<K24*1.2,"Watch","Stable"))) -> Danger | N24: =ROUND($B$5*(C24*(1+D$7))*SQRT($B$6/30),0) -> 6 | O24: =ROUND((B24*(1+D$7))*$B$6+N24,0) -> 9 | P24: =IF(E24="Missing",0,ROUND(E24/(B24*(1+D$7)),0)) -> 12 | Q24: =IF(E24="Missing","Missing",IF(E24<O24,"Danger",IF(E24<O24*1.2,"Watch","Stable"))) -> Danger
... A49: ='Inventory Analysis'!A41 -> PRD-040 | B49: ='Inventory Analysis'!F41 -> 0.14 | C49: ='Inventory Analysis'!E41 -> 2.5968831 | D49: =ROUND($B$5*C49*SQRT($B$6/30),0) -> 3 | E49: ='Inventory Analysis'!J41 -> 30 | F49: =ROUND($B$5*(C49*(1+B$7))*SQRT($B$6/30),0) -> 4 | G49: =ROUND((B49*(1+$B$7))*$B$6+F49,0) -> 6 | H49: =IF(E49="Missing",0,ROUND(E49/(B49*(1+$B$7)),0)) -> 171 | I49: =IF(E49="Missing","Missing",IF(E49<G49,"Danger",IF(E49<G49*1.2,"Watch","Stable"))) -> Stable | J49: =ROUND($B$5*(C49*(1+C$7))*SQRT($B$6/30),0) -> 4 | K49: =ROUND((B49*(1+$C$7))*$B$6+J49,0) -> 7 | L49: =IF(E49="Missing",0,ROUND(E49/(B49*(1+C$7)),0)) -> 143 | M49: =IF(E49="Missing","Missing",IF(E49<K49,"Danger",IF(E49<K49*1.2,"Watch","Stable"))) -> Stable | N49: =ROUND($B$5*(C49*(1+D$7))*SQRT($B$6/30),0) -> 5 | O49: =ROUND((B49*(1+D$7))*$B$6+N49,0) -> 8 | P49: =IF(E49="Missing",0,ROUND(E49/(B49*(1+D$7)),0)) -> 122 | Q49: =IF(E49="Missing","Missing",IF(E49<O49,"Danger",IF(E49<O49*1.2,"Watch","Stable"))) -> Stable
H51: Total anger | I51: =COUNTIF(I10:I49,"Danger") -> 6 | L51: Total anger | M51: =COUNTIF(M10:M49,"Danger") -> 7 | P51: Total anger | Q51: =COUNTIF(Q10:Q49,"Danger") -> 8
H52: Total Watch | I52: =COUNTIF(I10:I49,"Watch") -> 1 | L52: Total Watch | M52: =COUNTIF(M10:M49,"Watch") -> 3 | P52: Total Watch | Q52: =COUNTIF(Q10:Q49,"Watch") -> 4
H53: Total Stable | I53: =COUNTIF(I10:I49,"Stable") -> 29 | L53: Total Stable | M53: =COUNTIF(M10:M49,"Stable") -> 26 | P53: Total Stable | Q53: =COUNTIF(Q10:Q49,"Stable") -> 24
A56: What-If Modeling: Lead Time vs ROP (Data Table)
A58: Input
A59: Avg_Daily_Demand | B59: ='Inventory Analysis'!F18 -> 0.14
A60: Std_Dev | B60: ='Inventory Analysis'!E18 -> 6.4359527
A61: Z_Score | B61: 1.65
A62: Base_Lead_Time | B62: 14
A64: Driver Formula based on the base-lead time | B64: =ROUND((B59*B62)+(1.65*B60*SQRT(B62/30)),0) -> 9
A67: Lead_Time | B67: 7 | C67: 10 | D67: 14 | E67: 21 | F67: 28 | G67: 35 | H67: 45
A68: ROP | B68: =B64 -> 9 | C68: 8 | D68: 9 | E68: 12 | F68: 14 | G68: 16 | H68: 19
A72: Demand Spike Impact on Inventory: PRD-017
A75: SKU | B75: PRD-017
A76: Avg_Daily_Demand | B76: ='Inventory Analysis'!F18 -> 0.14
A77: Std_Dev | B77: ='Inventory Analysis'!E18 -> 6.4359527
A78: Units_On_Hand | B78: ='Inventory Analysis'!J18 -> 20
A79: Z_Score | B79: 1.65
A80: Lead_Time | B80: 14
A81: Spike_Factor | B81: 2
A84: Spiked_Daily_Demand | B84: =B76*B81 -> 0.28
A85: Days_to_Stockout | B85: =ROUND(B78/B84,0) -> 71
A86: ROP_at_Spike | B86: =ROUND((B84*B80)+(B79*B77*SQRT(B80/30)),0) -> 11
A87: Extra_Safety_Stock | B87: =ROUND((B79*B77*SQRT(B80/30))-(B79*B77*SQRT(B80/30)),0) -> 0
A90: Unit Margin × Velocity Matrix
A92: SKU_Code | B92: Avg_Daily_Demand | C92: Gross_Margin_Pct | D92: Quadrant | E92: Median_Demand | F92: =MEDIAN(B93:B132) -> 0.17
A93: {='Financial Analysis'!A2:A41} -> PRD-001 | B93: =_xlfn.XLOOKUP(A93,'Inventory Analysis'!A2:A41,'Inventory Analysis'!F2:F41) -> 0.12 | C93: =_xlfn.XLOOKUP(A93,'Financial Analysis'!A2:A41,'Financial Analysis'!H2:H41) -> 0.55952381 | D93: =IF(AND(B93>$F$92,C93>$F$93),"STAR",IF(AND(B93>$F$92,C93<=$F$93),"VOLUME DRIVER",IF(AND(B93<=$F$92,C93>$F$93),"SLEEPER","DEAD WEIGHT"))) -> SLEEPER | E93: Median_Margin | F93: =MEDIAN(C93:C132) -> 0.55942292
A94: PRD-002 | B94: =_xlfn.XLOOKUP(A94,'Inventory Analysis'!A3:A42,'Inventory Analysis'!F3:F42) -> 0.19 | C94: =_xlfn.XLOOKUP(A94,'Financial Analysis'!A3:A42,'Financial Analysis'!H3:H42) -> 0.55952381 | D94: =IF(AND(B94>$F$92,C94>$F$93),"STAR",IF(AND(B94>$F$92,C94<=$F$93),"VOLUME DRIVER",IF(AND(B94<=$F$92,C94>$F$93),"SLEEPER","DEAD WEIGHT"))) -> STAR
A95: PRD-003 | B95: =_xlfn.XLOOKUP(A95,'Inventory Analysis'!A4:A43,'Inventory Analysis'!F4:F43) -> 0.19 | C95: =_xlfn.XLOOKUP(A95,'Financial Analysis'!A4:A43,'Financial Analysis'!H4:H43) -> 0.55952381 | D95: =IF(AND(B95>$F$92,C95>$F$93),"STAR",IF(AND(B95>$F$92,C95<=$F$93),"VOLUME DRIVER",IF(AND(B95<=$F$92,C95>$F$93),"SLEEPER","DEAD WEIGHT"))) -> STAR
A96: PRD-004 | B96: =_xlfn.XLOOKUP(A96,'Inventory Analysis'!A5:A44,'Inventory Analysis'!F5:F44) -> 0.19 | C96: =_xlfn.XLOOKUP(A96,'Financial Analysis'!A5:A44,'Financial Analysis'!H5:H44) -> 0.56818182 | D96: =IF(AND(B96>$F$92,C96>$F$93),"STAR",IF(AND(B96>$F$92,C96<=$F$93),"VOLUME DRIVER",IF(AND(B96<=$F$92,C96>$F$93),"SLEEPER","DEAD WEIGHT"))) -> STAR
A97: PRD-005 | B97: =_xlfn.XLOOKUP(A97,'Inventory Analysis'!A6:A45,'Inventory Analysis'!F6:F45) -> 0.23 | C97: =_xlfn.XLOOKUP(A97,'Financial Analysis'!A6:A45,'Financial Analysis'!H6:H45) -> 0.56818182 | D97: =IF(AND(B97>$F$92,C97>$F$93),"STAR",IF(AND(B97>$F$92,C97<=$F$93),"VOLUME DRIVER",IF(AND(B97<=$F$92,C97>$F$93),"SLEEPER","DEAD WEIGHT"))) -> STAR
A98: PRD-006 | B98: =_xlfn.XLOOKUP(A98,'Inventory Analysis'!A7:A46,'Inventory Analysis'!F7:F46) -> 0.16 | C98: =_xlfn.XLOOKUP(A98,'Financial Analysis'!A7:A46,'Financial Analysis'!H7:H46) -> 0.56818182 | D98: =IF(AND(B98>$F$92,C98>$F$93),"STAR",IF(AND(B98>$F$92,C98<=$F$93),"VOLUME DRIVER",IF(AND(B98<=$F$92,C98>$F$93),"SLEEPER","DEAD WEIGHT"))) -> SLEEPER
A99: PRD-007 | B99: =_xlfn.XLOOKUP(A99,'Inventory Analysis'!A8:A47,'Inventory Analysis'!F8:F47) -> 0.18 | C99: =_xlfn.XLOOKUP(A99,'Financial Analysis'!A8:A47,'Financial Analysis'!H8:H47) -> 0.55813953 | D99: =IF(AND(B99>$F$92,C99>$F$93),"STAR",IF(AND(B99>$F$92,C99<=$F$93),"VOLUME DRIVER",IF(AND(B99<=$F$92,C99>$F$93),"SLEEPER","DEAD WEIGHT"))) -> VOLUME DRIVER
A100: PRD-008 | B100: =_xlfn.XLOOKUP(A100,'Inventory Analysis'!A9:A48,'Inventory Analysis'!F9:F48) -> 0.22 | C100: =_xlfn.XLOOKUP(A100,'Financial Analysis'!A9:A48,'Financial Analysis'!H9:H48) -> 0.55813953 | D100: =IF(AND(B100>$F$92,C100>$F$93),"STAR",IF(AND(B100>$F$92,C100<=$F$93),"VOLUME DRIVER",IF(AND(B100<=$F$92,C100>$F$93),"SLEEPER","DEAD WEIGHT"))) -> VOLUME DRIVER
A101: PRD-009 | B101: =_xlfn.XLOOKUP(A101,'Inventory Analysis'!A10:A49,'Inventory Analysis'!F10:F49) -> 0.22 | C101: =_xlfn.XLOOKUP(A101,'Financial Analysis'!A10:A49,'Financial Analysis'!H10:H49) -> 0.54761905 | D101: =IF(AND(B101>$F$92,C101>$F$93),"STAR",IF(AND(B101>$F$92,C101<=$F$93),"VOLUME DRIVER",IF(AND(B101<=$F$92,C101>$F$93),"SLEEPER","DEAD WEIGHT"))) -> VOLUME DRIVER
A102: PRD-010 | B102: =_xlfn.XLOOKUP(A102,'Inventory Analysis'!A11:A50,'Inventory Analysis'!F11:F50) -> 0.12 | C102: =_xlfn.XLOOKUP(A102,'Financial Analysis'!A11:A50,'Financial Analysis'!H11:H50) -> 0.54761905 | D102: =IF(AND(B102>$F$92,C102>$F$93),"STAR",IF(AND(B102>$F$92,C102<=$F$93),"VOLUME DRIVER",IF(AND(B102<=$F$92,C102>$F$93),"SLEEPER","DEAD WEIGHT"))) -> DEAD WEIGHT
A103: PRD-011 | B103: =_xlfn.XLOOKUP(A103,'Inventory Analysis'!A12:A51,'Inventory Analysis'!F12:F51) -> 0.13 | C103: =_xlfn.XLOOKUP(A103,'Financial Analysis'!A12:A51,'Financial Analysis'!H12:H51) -> 0.5625 | D103: =IF(AND(B103>$F$92,C103>$F$93),"STAR",IF(AND(B103>$F$92,C103<=$F$93),"VOLUME DRIVER",IF(AND(B103<=$F$92,C103>$F$93),"SLEEPER","DEAD WEIGHT"))) -> SLEEPER
A104: PRD-012 | B104: =_xlfn.XLOOKUP(A104,'Inventory Analysis'!A13:A52,'Inventory Analysis'!F13:F52) -> 0.14 | C104: =_xlfn.XLOOKUP(A104,'Financial Analysis'!A13:A52,'Financial Analysis'!H13:H52) -> 0.5625 | D104: =IF(AND(B104>$F$92,C104>$F$93),"STAR",IF(AND(B104>$F$92,C104<=$F$93),"VOLUME DRIVER",IF(AND(B104<=$F$92,C104>$F$93),"SLEEPER","DEAD WEIGHT"))) -> SLEEPER
A105: PRD-013 | B105: =_xlfn.XLOOKUP(A105,'Inventory Analysis'!A14:A53,'Inventory Analysis'!F14:F53) -> 0.17 | C105: =_xlfn.XLOOKUP(A105,'Financial Analysis'!A14:A53,'Financial Analysis'!H14:H53) -> 0.57142857 | D105: =IF(AND(B105>$F$92,C105>$F$93),"STAR",IF(AND(B105>$F$92,C105<=$F$93),"VOLUME DRIVER",IF(AND(B105<=$F$92,C105>$F$93),"SLEEPER","DEAD WEIGHT"))) -> SLEEPER
... A132: PRD-040 | B132: =_xlfn.XLOOKUP(A132,'Inventory Analysis'!A41:A80,'Inventory Analysis'!F41:F80) -> 0.14 | C132: =_xlfn.XLOOKUP(A132,'Financial Analysis'!A41:A80,'Financial Analysis'!H41:H80) -> 0.56043956 | D132: =IF(AND(B132>$F$92,C132>$F$93),"STAR",IF(AND(B132>$F$92,C132<=$F$93),"VOLUME DRIVER",IF(AND(B132<=$F$92,C132>$F$93),"SLEEPER","DEAD WEIGHT"))) -> SLEEPER

Sheet Dashboard - Operations
A1: Tankhoone Fashion Retail — Operations & Inventory Dashboard
A2: Tehran 2023 | Inventory Health | Reorder Alerts | SKU Action Plan
A3: Report Date: | B3: =TODAY() -> 46099
B5: SKUs Reorder Now | D5: Dead Weight SKUs | F5: Star SKUs | H5: SKUs at Spike Danger | J5: Avg Days of Supply
B6: =COUNTIF('Inventory Analysis'!M2:M41,"Reorder Now") -> 6 | D6: =COUNTIF('Advanced Analysis'!D93:D132,"DEAD WEIGHT") -> 14 | F6: =COUNTIF('Advanced Analysis'!D93:D132,"STAR") -> 11 | H6: =COUNTIF('Advanced Analysis'!I10:I49,"Danger") -> 6 | J6: =ROUND(AVERAGE('Inventory Analysis'!K2:K41),0) -> 12
A10: 🚨 Reorder Now — 6 SKUs Require Immediate Action
A11: SKU_Code | B11: Product_Name | C11: Units_On_Hand | D11: ROP | E11: Days_of_Supply | F11: Stock_Status
A12: ='Inventory Analysis'!A2 -> PRD-001 | B12: ='Inventory Analysis'!B2 -> Beige Co-ord Set | C12: ='Inventory Analysis'!J2 -> 3 | D12: ='Inventory Analysis'!H2 -> 3 | E12: ='Inventory Analysis'!K2 -> 8 | F12: ='Inventory Analysis'!M2 -> Reorder Now
A13: ='Inventory Analysis'!A4 -> PRD-003 | B13: ='Inventory Analysis'!B4 -> Beige Co-ord Set | C13: ='Inventory Analysis'!J4 -> 4 | D13: ='Inventory Analysis'!H4 -> 4 | E13: ='Inventory Analysis'!K4 -> 10 | F13: ='Inventory Analysis'!M4 -> Reorder Now
A14: ='Inventory Analysis'!A10 -> PRD-009 | B14: ='Inventory Analysis'!B10 -> Red Sweatshirt | C14: ='Inventory Analysis'!J10 -> 2 | D14: ='Inventory Analysis'!H10 -> 4 | E14: ='Inventory Analysis'!K10 -> 7 | F14: ='Inventory Analysis'!M10 -> Reorder Now
A15: ='Inventory Analysis'!A16 -> PRD-015 | B15: ='Inventory Analysis'!B16 -> Cable Knit Vest White | C15: ='Inventory Analysis'!J16 -> 3 | D15: ='Inventory Analysis'!H16 -> 3 | E15: ='Inventory Analysis'!K16 -> 11 | F15: ='Inventory Analysis'!M16 -> Reorder Now
A16: ='Inventory Analysis'!A31 -> PRD-030 | B16: ='Inventory Analysis'!B31 -> Magenta Abaya Dress | C16: ='Inventory Analysis'!J31 -> 5 | D16: ='Inventory Analysis'!H31 -> 5 | E16: ='Inventory Analysis'!K31 -> 19 | F16: ='Inventory Analysis'!M31 -> Reorder Now
A17: ='Inventory Analysis'!A39 -> PRD-038 | B17: ='Inventory Analysis'!B39 -> Grey Maxi Dress | C17: ='Inventory Analysis'!J39 -> 3 | D17: ='Inventory Analysis'!H39 -> 3 | E17: ='Inventory Analysis'!K39 -> 10 | F17: ='Inventory Analysis'!M39 -> Reorder Now
G18: ⚠ Demand Spike Risk — 25% Scenario
G19: SKU_Code | H19: Units_On_Hand | I19: ROP_25% | J19: Stockout_25%
G20: ='Advanced Analysis'!A10 -> PRD-001 | H20: ='Advanced Analysis'!E10 -> 3 | I20: ='Advanced Analysis'!G10 -> 6 | J20: ='Advanced Analysis'!I10 -> Danger
G21: ='Advanced Analysis'!A12 -> PRD-003 | H21: ='Advanced Analysis'!E12 -> 4 | I21: ='Advanced Analysis'!G12 -> 8 | J21: ='Advanced Analysis'!I12 -> Danger
G22: ='Advanced Analysis'!A18 -> PRD-009 | H22: ='Advanced Analysis'!E18 -> 2 | I22: ='Advanced Analysis'!G18 -> 9 | J22: ='Advanced Analysis'!I18 -> Danger
G23: ='Advanced Analysis'!A24 -> PRD-015 | H23: ='Advanced Analysis'!E24 -> 3 | I23: ='Advanced Analysis'!G24 -> 6 | J23: ='Advanced Analysis'!I24 -> Danger
G24: ='Advanced Analysis'!A39 -> PRD-030 | H24: ='Advanced Analysis'!E39 -> 5 | I24: ='Advanced Analysis'!G39 -> 9 | J24: ='Advanced Analysis'!I39 -> Danger
G25: ='Advanced Analysis'!A47 -> PRD-038 | H25: ='Advanced Analysis'!E47 -> 3 | I25: ='Advanced Analysis'!G47 -> 6 | J25: ='Advanced Analysis'!I47 -> Danger

Sheet Dashboard - Performance
A1: Tankhoone Fashion Retail — Business Performance Dashboard
A2: Tehran 2023 | 40 SKUs | ~1,215 Transactions | Analysis by Hamed
A3: Report Date: | B3: =TODAY() -> 46099
B6: Total Revenue (IRR) | D6: Avg Gross Margin | F6: Total SKUs | H6: Class A SKUs | J6: Avg Sell-Through
B7: =SUM('Financial Analysis'!I2:I41) -> 593714300 | D7: =AVERAGE('Financial Analysis'!H2:H41) -> 0.55967674 | F7: =COUNTA('Financial Analysis'!A2:A41) -> 40 | H7: 20 | J7: =AVERAGE('Financial Analysis'!E2:E41) -> 0.90629418

Sheet CLEAN_Sales
A1: Order_ID | B1: SaleDate | C1: SKU_Code | D1: Product Name | E1: Category | F1: Size | G1: Qty | H1: UnitPrice_IRR | I1: Discount | J1: Channel | K1: Revenue
A2: ORD-1539 | B2: 45068 | C2: PRD-002 | D2: Beige Co-ord Set | E2: Co-ord Sets | F2: M | G2: 4 | H2: 420000 | I2: 10 | J2: in-store | K2: =G2*H2*(1-I2/100) -> 1512000
A3: ORD-1887 | B3: 45072 | C3: PRD-003 | D3: Beige Co-ord Set | E3: Co-ord Sets | F3: Unknown | G3: 1 | H3: 420000 | I3: 0 | J3: Instagram DM | K3: =G3*H3*(1-I3/100) -> 420000
A4: ORD-1545 | B4: 45248 | C4: PRD-033 | D4: Beige Knit Cardigan | E4: Knitwear | F4: M | G4: 3 | H4: 265000 | I4: 0 | J4: In-Store | K4: =G4*H4*(1-I4/100) -> 795000
A5: ORD-1049 | B5: 45002 | C5: PRD-040 | D5: Navy Wide Leg Pants | E5: Bottoms | F5: M | G5: 1 | H5: 182000 | I5: 10 | J5: Instagram DM | K5: =G5*H5*(1-I5/100) -> 163800
A6: ORD-1320 | B6: 45062 | C6: PRD-009 | D6: Red Sweatshirt | E6: Sweatshirts | F6: M | G6: 2 | H6: 210000 | I6: 0 | J6: In-Store | K6: =G6*H6*(1-I6/100) -> 420000
A7: ORD-1127 | B7: 45279 | C7: PRD-008 | D7: Olive Sweatshirt | E7: Sweatshirts | F7: L | G7: -1 | H7: 215000 | I7: 10 | J7: Instagram DM | K7: =G7*H7*(1-I7/100) -> -193500
A8: ORD-1202 | B8: 45064 | C8: PRD-020 | D8: Striped Shirt | E8: Shirts | F8: M | G8: 1 | H8: 198000 | I8: 0 | J8: Instagram DM | K8: =G8*H8*(1-I8/100) -> 198000
A9: ORD-1824 | B9: 45178 | C9: PRD-011 | D9: Burgundy Knit Dress | E9: Knit Dresses | F9: M | G9: 1 | H9: 320000 | I9: 0 | J9: Telegram | K9: =G9*H9*(1-I9/100) -> 320000
A10: ORD-1065 | B10: 45129 | C10: PRD-017 | D10: Grey Hoodie | E10: Sweatshirts | F10: L | G10: 1 | H10: 235000 | I10: 5 | J10: Instagram DM | K10: =G10*H10*(1-I10/100) -> 223250
A11: ORD-2022 | B11: 44986 | C11: PRD-016 | D11: Grey Hoodie | E11: sweatshirts | F11: M | G11: 1 | H11: 235000 | I11: 0 | J11: telegram | K11: =G11*H11*(1-I11/100) -> 235000
A12: ORD-1966 | B12: 45239 | C12: PRD-004 | D12: Pink Sweatshirt | E12: Sweatshirts | F12: S | G12: 4 | H12: 220000 | I12: 0 | J12: In-Store | K12: =G12*H12*(1-I12/100) -> 880000
A13: ORD-1767 | B13: 45283 | C13: PRD-019 | D13: White Linen Shirt | E13: shirts | F13: M | G13: 2 | H13: 195000 | I13: 10 | J13: In-Store | K13: =G13*H13*(1-I13/100) -> 351000
... A1190: ORD-1807 | B1190: 45228 | C1190: PRD-015 | D1190: Cable Knit Vest White | E1190: Knitwear | F1190: M | G1190: 4 | H1190: 260000 | I1190: 0 | J1190: in-store | K1190: =G1190*H1190*(1-I1190/100) -> 1040000

Sheet  CLEAN_Products
A1: SKU_Code | B1: Product_Name | C1: Category | D1: Colour | E1: Size_Code | F1: Cost_IRR | G1: RRP_IRR | H1: Vendor_Name | I1: Item_Status
A2: PRD-001 | B2: Beige Co-ord Set | C2: Co-ord Sets | D2: Beige | E2: S | F2: 185000 | G2: 420000 | H2: Tejarat Pars Co. | I2: Active
A3: PRD-002 | B3: Beige Co-ord Set | C3: Co-ord Sets | D3: Beige | E3: M | F3: 185000 | G3: 420000 | H3: Tejarat Pars Co. | I3: Active
A4: PRD-003 | B4: Beige Co-ord Set | C4: Co-ord Sets | D4: Beige | E4: L | F4: 185000 | G4: 420000 | H4: Tejarat Pars Co. | I4: Active
A5: PRD-004 | B5: Pink Sweatshirt | C5: Sweatshirts | D5: Pink | E5: S | F5: 95000 | G5: 220000 | H5: Arya Textile | I5: Active
A6: PRD-005 | B6: Pink Sweatshirt | C6: Sweatshirts | D6: Pink | E6: M | F6: 95000 | G6: 220000 | H6: Arya Textile | I6: Unknown
A7: PRD-006 | B7: Pink Sweatshirt | C7: Sweatshirts | D7: Pink | E7: L | F7: 95000 | G7: 220000 | H7: Arya Textile | I7: Unknown
A8: PRD-007 | B8: Olive Sweatshirt | C8: Sweatshirts | D8: Olive | E8: M | F8: 95000 | G8: 215000 | H8: Arya Textile | I8: Active
A9: PRD-008 | B9: Olive Sweatshirt | C9: Sweatshirts | D9: Olive | E9: L | F9: 95000 | G9: 215000 | H9: Arya Textile | I9: Unknown
A10: PRD-009 | B10: Red Sweatshirt | C10: Sweatshirts | D10: Red | E10: M | F10: 95000 | G10: 210000 | H10: Arya Textile | I10: Inactive
A11: PRD-010 | B11: Blue Sweatshirt | C11: Sweatshirts | D11: Blue | E11: M | F11: 95000 | G11: 210000 | H11: Arya Textile | I11: Active
A12: PRD-011 | B12: Burgundy Knit Dress | C12: Knit Dresses | D12: Burgundy | E12: M | F12: 140000 | G12: 320000 | H12: Kian Knit Factory | I12: Active
A13: PRD-012 | B13: Burgundy Knit Dress | C13: Knit Dresses | D13: Burgundy | E13: L | F13: 140000 | G13: 320000 | H13: Kian Knit Factory | I13: Inactive
... A41: PRD-040 | B41: Navy Wide Leg Pants | C41: Bottoms | D41: Navy | E41: M | F41: 80000 | G41: 182000 | H41: Saba Fashion | I41: active

Sheet  CLEAN_Inventory
A1: SKU_Code | B1: Ordered_Qty | C1: Received_Qty | D1: Receipt_Date | E1: Units_On_Hand | F1: Reorder_Lvl | G1: Storage_Location | H1: Notes
A2: PRD-001 | B2: 82 | C2: 82 | D2: 44866 | E2: 3 | F2: 8 | G2: Warehouse A | H2: Slow mover
A3: PRD-002 | B3: 134 | C3: 134 | D3: 44898 | E3: 23 | F3: 5 | G3: Warehouse A
A4: PRD-003 | B4: 33 | C4: 33 | D4: 44893 | E4: 4 | F4: 10 | G4: Warehouse A | H4: Check with supplier
A5: PRD-004 | B5: 84 | C5: 39 | D5: 44845 | E5: 13 | F5: 8 | H5: Storage_Location missing — stock on hand confirmed — physical location unknown — exclude from pick efficiency analysis
A6: PRD-005 | B6: 51 | C6: 51 | D6: 44838 | E6: 22 | F6: 11 | G6: Warehouse A | H6: End of season
A7: PRD-006 | B7: 146 | C7: 146 | D7: 44916 | E7: 40 | F7: 10 | G7: Warehouse B | H7: Slow mover
A8: PRD-007 | B8: 135 | C8: 135 | D8: 44915 | E8: 9 | F8: 11 | G8: Warehouse A
A9: PRD-008 | B9: 119 | C9: 119 | D9: 44915 | F9: 10 | G9: Warehouse B | H9: Check with supplier-Units_On_Hand missing — received 2022, report Jan 2024 — 12+ months of sales unaccounted for — exclude from stock calculations
A10: PRD-009 | B10: 58 | C10: 58 | D10: 44879 | E10: 2 | F10: 7 | G10: Warehouse A
A11: PRD-010 | B11: 95 | C11: 95 | D11: 44911 | E11: 10 | F11: 8 | G11: Warehouse A
A12: PRD-011 | B12: 92 | C12: 92 | D12: 44869 | E12: 35 | F12: 16 | G12: Warehouse A
A13: PRD-012 | B13: 139 | C13: 139 | D13: 44909 | E13: 16 | F13: 13 | G13: Warehouse B
A14: PRD-013 | B14: 46 | C14: 46 | D14: 44857 | E14: 10 | F14: 9 | G14: Warehouse B
A15: PRD-014 | B15: 62 | C15: 62 | D15: 44883 | E15: 40 | F15: 9 | H15: Slow mover.Storage_Location missing — stock on hand confirmed — physical location unknown — exclude from pick efficiency analysis
A16: PRD-015 | B16: 37 | C16: 37 | D16: 44906 | E16: 3 | F16: 11 | G16: Warehouse A
A17: PRD-016 | B17: 38 | C17: 38 | D17: 44852 | E17: 31 | F17: 6 | G17: Warehouse A | H17: Slow mover
A18: PRD-017 | B18: 139 | C18: 139 | E18: 20 | F18: 8 | G18: Warehouse A | H18: Receipt date missing — units on hand confirm goods received
A19: PRD-018 | B19: 129 | C19: 129 | D19: 44887 | E19: 18 | F19: 6 | G19: Warehouse B | H19: Storage_Location missing — stock on hand confirmed — physical location unknown — exclude from pick efficiency analysis
A20: PRD-019 | B20: 79 | C20: 66 | D20: 44891 | F20: 20 | G20: Warehouse A | H20: Partial receipt — 13 units short from supplier. Units_On_Hand missing — received 2022, report Jan 2024 — 12+ months of sales unaccounted for — exclude from stock calculations
A21: PRD-020 | B21: 77 | C21: 66 | D21: 44631 | E21: 21 | F21: 7 | H21: Partial receipt — 11 units short from supplier
A22: PRD-021 | B22: 105 | C22: 105 | D22: 44906 | E22: 22 | F22: 19 | G22: Warehouse A | H22: Storage_Location missing — stock on hand confirmed — physical location unknown — exclude from pick efficiency analysis
A23: PRD-022 | B23: 32 | C23: 32 | E23: 31 | F23: 5 | G23: Warehouse A | H23: Receipt date missing — units on hand confirm goods received
A24: PRD-023 | B24: 69 | C24: 32 | D24: 44903 | E24: 39 | F24: 18 | H24: Storage_Location missing — stock on hand confirmed — physical location unknown — exclude from pick efficiency analysis
A25: PRD-024 | B25: 34 | C25: 34 | D25: 44911 | E25: 27 | F25: 11 | G25: Warehouse A
A26: PRD-025 | B26: 86 | C26: 86 | D26: 44920 | E26: 21 | F26: 5 | H26: Storage_Location missing — stock on hand confirmed — physical location unknown — exclude from pick efficiency analysis
A27: PRD-026 | B27: 75 | C27: 75 | E27: 38 | F27: 14 | G27: Warehouse B | H27: Slow mover-Receipt date missing — units on hand confirm goods received
A28: PRD-027 | B28: 54 | C28: 36 | E28: 7 | F28: 15 | G28: Warehouse B | H28: Receipt date missing — units on hand confirm goods received
A29: PRD-028 | B29: 137 | C29: 64 | D29: 44891 | E29: 18 | F29: 17 | H29: Reorder ASAP.Storage_Location missing — stock on hand confirmed — physical location unknown — exclude from pick efficiency analysis
A30: PRD-029 | B30: 30 | C30: 30 | D30: 44839 | E30: 29 | F30: 18 | H30: End of season.Storage_Location missing — stock on hand confirmed — physical location unknown — exclude from pick efficiency analysis
A31: PRD-030 | B31: 81 | C31: 81 | D31: 44884 | E31: 5 | F31: 19 | H31: Slow mover.Storage_Location missing — stock on hand confirmed — physical location unknown — exclude from pick efficiency analysis
A32: PRD-031 | B32: 118 | C32: 118 | D32: 44893 | H32: Check with supplier. Units_On_Hand missing — received 2022, report Jan 2024 — 12+ months of sales unaccounted for — exclude from stock calculations.Storage_Location missing — stock on hand confirmed — physical location unknown — exclude from pick efficiency analysis.Units_On_Hand missing — received 2022, report Jan 2024 — 12+ months of sales unaccounted for — Reorder_Level missing — exclude from stock calculations and replenishment planning
A33: PRD-032 | B33: 55 | C33: 43 | D33: 44874 | E33: 29 | F33: 18 | G33: Warehouse A | H33: Slow mover
A34: PRD-033 | B34: 102 | C34: 102 | D34: 44845 | F34: 11 | G34: Warehouse B | H34: Units_On_Hand missing — received 2022, report Jan 2024 — 12+ months of sales unaccounted for — exclude from stock calculations
A35: PRD-034 | B35: 74 | C35: 74 | D35: 44901 | E35: 13 | F35: 19 | G35: Warehouse B | H35: Slow mover
A36: PRD-035 | B36: 147 | C36: 147 | D36: 44922 | E36: 22 | F36: 15 | G36: Warehouse B | H36: Check with supplier
A37: PRD-036 | B37: 72 | C37: 72 | D37: 44889 | E37: 16 | F37: 12 | G37: Warehouse A | H37: End of season
A38: PRD-037 | B38: 126 | C38: 126 | D38: 44923 | E38: 28 | F38: 13 | G38: Warehouse B | H38: End of season
A39: PRD-038 | B39: 32 | C39: 32 | D39: 44922 | E39: 3 | F39: 10 | G39: Warehouse A
A40: PRD-039 | B40: 103 | C40: 103 | E40: 10 | F40: 13 | G40: Warehouse A | H40: Receipt date missing — units on hand confirm goods received
A41: PRD-040 | B41: 37 | C41: 37 | D41: 44862 | E41: 30 | F41: 20 | H41: Reorder ASAP.Storage_Location missing — stock on hand confirmed — physical location unknown — exclude from pick efficiency analysis

Sheet Notes
A1: # | B1: Chapter | C1: What I Found | D1: Why It Happened | E1: Action Taken
A2: 1 | B2: 2 | C2: 26 rows had Qty = 0 | D2: Incomplete or cancelled entries with no business value | E2: Deleted from CLEAN_Sales
A3: 2 | B3: 2 | C3: Negative Qty rows exist | D3: Customer returns logged as negative transactions | E3: Kept — they represent real return transactions, reduce net sales correctly
A4: 3 | B4: 2 | C4: 10 rows had Product Name = 0 or blank | D4: Original POS data entered 0 instead of product name | E4: Fixed using XLOOKUP from CLEAN_Products on SKU_Code
A5: 4 | B5: 2 | C5: Lower case | E5: In CLEAN_Products, standardize PRD-019 category to Shirts
A6: 5 | B6: 2 | C6: SKU_Code had 3 different delimiters in CLEAN_Products | D6: Inconsistent data entry at source (dash, dot, space) | E6: Fixed using Find & Replace — standardized all to dash
A7: 6 | B7: 2 | C7: Category blanks in CLEAN_Sales | D7: Sales POS didn't always capture category | E7: Fixed using XLOOKUP from CLEAN_Products on SKU_Code
A8: 7 | B8: 2 | C8: CLEAN_Inventory had 2 junk rows at top and 3 footer rows at bottom | D8: WMS system exports include auto-generated header and summary footer rows | E8: Removed all junk rows. Used footer row count (40 SKUs) as sanity check
A9: 8 | B9: 2 | C9: Lowercase SKU codes in Inventory (prd-012, prd-024) | D9: Manual data entry in WMS did not enforce uppercase formatting | E9: Fixed using UPPER() formula, then Paste Special — Values Only
A10: 9 | B10: 2 | C10: Mixed date formats in Inventory Receipt_Date (3 formats) | D10: Data entered across different time periods with no enforced date format | E10: Standardized to DD/MM/YYYY using nested IF + DATE() formula in helper column Receipt_Date_Clean
A11: 10 | B11: 2 | C11: 5 rows missing Receipt_Date in Inventory | D11: Shipments received without date being logged in WMS at time of receipt | E11: Flagged in Notes column. SKUs 017, 022, 026, 027, 039 excluded from lead time calculations
A12: 11 | B12: 2 | C12: 4 rows missing Units_On_Hand in Inventory | D12: Items received in 2022 — 12+ months of unknown sales made current stock unverifiable | E12: Left blank — never fabricate stock. SKUs 008, 019, 031, 033 excluded from Days of Supply and ROP
A13: 12 | B13: 2 | C13: 10 rows missing Storage_Location in Inventory | D13: Items physically in stock but never assigned a bin location — operational gap, not just a data gap | E13: Flagged in Notes. SKUs 004,014,020,023,025,028,029,030,031,040 excluded from pick efficiency analysis
A14: 13 | B14: 2 | C14: PRD-031 had 3 critical fields all missing (Units_On_Hand, Storage_Location, Reorder_Level) | D14: SKU likely never properly onboarded into WMS — incomplete record from the start | E14: Excluded PRD-031 from ALL calculations — too unreliable for any analysis
A15: 14 | B15: 2 | C15: Item_Status casing inconsistent in CLEAN_Products (Active vs ACTIVE) | D15: ERP records updated by different users with no enforced casing rule | E15: Fixed using PROPER() / UPPER() formula, then Paste Special — Values Only in Item_Status column
A16: 15 | B16: 2 | C16: Created_Date and Last_Modified columns dropped from CLEAN_Products | D16: System metadata not needed for retail analytics — added clutter and confusion risk | E16: Deleted both columns. Kept only analysis-relevant fields
A17: 16 | B17: 2 | C17: Join keys mismatched across all 3 files (ProductID, Item_Code, SKU_Code) | D17: Each source system (POS, ERP, WMS) used its own internal naming for the product key | E17: Renamed ProductID (Sales) and Item_Code (Products) to SKU_Code — all 3 files now joinable on one unified key
A18: 17 | B18: 2 | C18: PRD-019 partial receipt — 66 of 79 units received from supplier | D18: Supplier shipped short — 13 units never arrived, possibly back-ordered or lost in transit | E18: Noted in Notes column. Used actual received qty (66) in all calculations, never the ordered qty (79)
C19: 6 rows had 0 in Category due to ghost blank cell causing column shift. | E19: Fixed manually after verifying against CLEAN_Products.
B20: 4 | D20: 3-month moving average not calculated due to insufficient data points per SKU and the seasonal nature of Tehran fashion demand. In a production environment, weekly Rate of Sale and Sell-Through Rate would replace this analysis

Sheet Findings
B5: chapter4 d- demand analysis | C5: Finding #1: Every category shows High volatility CV — demand is unpredictable across the entire assortment. Tehran fashion retail demand is inherently hard to forecast. Finding #2: Co-ord Sets and Sweatshirts combine highest revenue with highest count of volatile SKUs — priority candidates for safety stock in Chapter 5. | D5: Co-ord Sets and Sweatshirts are both your highest revenue categories AND your most volatile — that's a critical risk finding. High revenue + high volatility = stockout risk if you don't build safety stock buffers. Skirts and Bottoms being stable makes sense — they're your lowest revenue categories too.
B7: chapter4 d- Trend analysis by SLOPE | C7: Linear trend analysis returned flat results across all SKUs due to seasonal demand patterns interfering with slope calculation in a 12-month window. Demand volatility (CV) is a more meaningful metric for this dataset than directional trend.
B11: Chapter 5-Inventory analysis | C11: # | D11: Finding | E11: Business Reason | F11: Decision Supported
C12: 1 | D12: 6 SKUs require immediate reorder | E12: Stock fallen below ROP | F12: Trigger reorder for Co-ord Sets, Sweatshirts, Dresses priority SKUs
C13: 2 | D13: High CV categories (Ch.4) align with reorder triggers | E13: Volatile demand depletes stock faster and unpredictably | F13: Safety stock buffers must be reviewed each season
C14: 3 | D14: 4 SKUs missing Units_On_Hand (PRD-008,019,031,033) | E14: Data not captured in inventory system | F14: Cannot assess stock status — flag for urgent data collection
C15: 4 | D15: Lead time assumed at 14 days for all SKUs | E15: Order date not recorded in source system | F15: In production, capture order date at POS/ERP level
C16: Finding #16 — Gross Margin Range "Gross margin % ranges from 51% to 58% across all 40 SKUs — a narrow band indicating consistent supplier pricing and markup strategy. No outlier SKUs with dangerously thin or unusually high margins."
B17: chapter 6-Financial analysis
C18: Finding #17 — Sell-Through Anomalies "Several SKUs exceed 100% sell-through rate. Investigated and documented as opening inventory effect — units sold include stock carried over before the measurement period began, not a data error."
C20: Finding #18 — Revenue-Based ABC Classification "20 Class A SKUs drive 70% of total revenue. 12 Class B SKUs contribute the next 20%. 8 Class C SKUs account for the remaining 10%. Revenue is moderately concentrated — top 20 SKUs require priority protection in buying and inventory planning."
C22: Finding #19 — GMROI vs Revenue ABC Gap "Revenue-based ABC classified 20 SKUs as Class A. GMROI-based classification identifies only 5 Class A SKUs (GMROI ≥ 2.0), 13 Class B (1.0–1.99), and 22 Class C (below 1.0). The gap indicates widespread capital inefficiency masked by revenue performance. A production model would adjust GMROI for trade credit terms (net 30) and qualitative overlays for halo-effect and supply-chain-constrained SKUs."

Sheet  Excel Skills Practiced table
C3: Skill | D3: Where Used
C4: PivotTable from CLEAN_Sales | D4: Summarized 1,215 rows into monthly, category, channel, SKU views
C5: PivotChart — Clustered Column | D5: Built Monthly Revenue and Orders & Qty charts
C6: PivotChart — Horizontal Bar | D6: Built Channel and Top 10 SKU charts
C7: PivotChart — Pie Chart | D7: Built Category revenue distribution chart
C8: Top 10 Value Filter in Pivot | D8: Filtered pivot to show only Top 10 SKUs by revenue
C9: Date Grouping in Pivot | D9: Grouped SaleDate by Month automatically
C10: TEXT() helper column | D10: Created Month column to avoid serial number display in pivot
C11: MONTH() formula | D11: Extracted month number for sorting
C12: Paste Special — Picture | D12: Converted live PivotChart to static image to lock series
C13: Manual cell fix | D13: Fixed 6 rows with ghost blank cell causing column shift
C14: Pivot cache refresh | D14: Refreshed pivot to clear old cached values after source data fix
... C33: Rounding discipline | D33: Kept 2 decimal places in intermediate calculations (Avg_Daily_Demand), rounded to 0 only in final outputs (ROP, Safety Stock) — units are whole pieces
